Workbook

Sheet README
A1: LBG x UK NBSAP nature priorities – proof of concept
A2: Purpose | B2: Map Lloyds Banking Group (LBG) public nature-related disclosures to the UK NBSAP themes and sub-themes in the EY NBSAP Nature Sizing workbook, score priorities with a fixed rubric, and support a 3-slide summary.
A3: As at | B3: 7 October 2026
A4: Status | B4: Proof of concept. Based on two LBG public reports only; findings must be validated against LBG annual and sustainability reporting before external use.
A5: Taxonomy | B5: Theme (5) > Sub-theme (15, = "Markets" in the EY workbook) > Sub-market (80). Theme names are inferred from the market codes (W, AFF, UD, DM, P) and should be confirmed.
A6: How scores work | B6: Scoring tab. C1, C2 and C4 are analyst judgements (blue text) with rationale and Evidence_IDs. C3 and C5 are calculated from the UK NBSAP commitments in the EY workbook. Weights and bands sit in the Rubric tab and drive every score, tier and rank.
A7: Colour legend | B7: Blue text = analyst input. Black = formula. Green = pulled from another tab. Yellow fill = assumption to confirm.
A8: Tabs | B8: Inputs | Sources | Taxonomy | NBSAP_Commitments | Evidence_Log | NBSAP_Mapping | Rubric | Scoring | Data_QA | QA_Log
A9: Reuse for a new client | B9: Replace Inputs, Sources, Evidence_Log and NBSAP_Mapping; re-enter C1, C2 and C4 in Scoring; repoint NBSAP_Commitments to the new country. Keep Rubric unchanged for comparability.
A10: Important caveat | B10: NBSAP commitment values are indicative: they combine programmes with different timeframes and some may overlap (see Data_QA). Use them to compare sub-themes, not as an additive market size.

Sheet Inputs
A1: Inputs
A4: Field | B4: Value | C4: Note
A5: Client | B5: Lloyds Banking Group (LBG)
A6: Country | B6: United Kingdom | C6: UK NBSAP = Environmental Improvement Plan 2025 (per EY workbook, Countries tab)
A7: Sector | B7: Banking and financial services
A8: Audience | B8: Internal (EY partner) | C8: Assumed – confirm
A9: As-at date | B9: 07/10/2026
A10: Prepared by | B10: EY CCaSS (proof of concept) | C10: No individual names in client outputs

Sheet Sources
A1: Sources
A4: Source_ID | B4: Title | C4: Publisher | D4: Year | E4: Type | F4: Location | G4: Date accessed | H4: Included | I4: Reason / note
A5: SRC-01 | B5: Working with nature: Integrating nature-based solutions across urban environments and landscapes | C5: Lloyds Banking Group, with input from the RSPB | D5: 2024 | E5: Thought leadership / position paper | F5: working-with-nature-report.pdf (provided by user) | G5: 07/10/2026 | H5: Y | I5: Published Oct 2024; at the edge of the 24-month window – still the most recent LBG nature-specific paper provided.
A6: SRC-02 | B6: Built to Last: Climate resilient infrastructure needs transformative investment | C6: Lloyds Banking Group | D6: 2026 | E6: Thought leadership / position paper | F6: lbg-built-to-last-report.pdf (provided by user) | G6: 07/10/2026 | H6: Y | I6: Published Sep 2026. Includes three LBG-financed case studies.
A7: SRC-03 | B7: NBSAP PowerBI Excel (NBSAP Nature Sizing tool input workbook) | C7: EY CCaSS (internal) | D7: 2025 | E7: NBSAP mapping / market sizing | F7: NBSAP_PowerBI_Excel.xlsx (provided by user) | G7: 07/10/2026 | H7: Y | I7: UK rows only (Country_ID = GBR). Underlying NBSAP: Environmental Improvement Plan 2025.
A8: — | B8: LBG Annual Report, Sustainability Report, climate/TNFD disclosures | C8: Lloyds Banking Group | D8: — | E8: Annual / sustainability reporting | F8: Not provided | G8: — | H8: N | I8: Not in scope of this POC. Recommended next step to validate C1 and C2 scores.

Sheet Taxonomy
A1: Taxonomy – themes and sub-themes (from EY NBSAP workbook)
A2: Theme names inferred from codes – confirm. NBSAP link: only W01 is referenced in the EY workbook; others are indicative and must be verified against EIP 2025.
A4: Theme_ID | B4: Theme | C4: SubTheme_ID | D4: Sub-theme | E4: Definition | F4: ENCORE theme | G4: Sub-markets | H4: UK NBSAP link | I4: UK NBSAP commitments (no.) | J4: UK NBSAP commitments (£bn) | K4: Market_Opportunity_Score
A5: W | B5: Water | C5: W01 | D5: Water usage | E5: Ensuring a sustainable supply of water to homes, the public and businesses | F5: Volume of water use | G5: WU01 AgTech and irrigation efficiency; WU02 Leak detection systems; WU03 Smart meters; WU04 Water cycle digitalisation; WU07 Industrial process water efficiency; WU08 Nuclear cooling water efficiency | H5: Goal 3: Water (EY workbook, p.47) | I5: =COUNTIF(NBSAP_Commitments!$E:$E,C5) -> 4 | J5: =SUMIF(NBSAP_Commitments!$E:$E,C5,NBSAP_Commitments!$H:$H)/1000000000 -> 0.174 | K5: =IF(J5>=Rubric!$C$29,5,IF(J5>=Rubric!$C$30,4,IF(J5>=Rubric!$C$31,3,IF(J5>=Rubric!$C$32,2,1)))) -> 2
A6: W | B6: Water | C6: W02 | D6: Water quality | E6: Water quality refers to the chemical, physical, and biological characteristics of water, assessed in relation to its suitability for a specific use, such as drinking, ecosystem support, agriculture, industry, or recreation. | F6: Emissions of toxic pollutants to water and soil | G6: WU09 Wastewater treatment; WU10 Desalination; WU11 Water body conservation; WU12 Marine and coastal area protection; WU13 Groundwater abstraction; WU14 Wetland and peatland restoration and protection | H6: Goal 3: Water (indicative) | I6: =COUNTIF(NBSAP_Commitments!$E:$E,C6) -> 5 | J6: =SUMIF(NBSAP_Commitments!$E:$E,C6,NBSAP_Commitments!$H:$H)/1000000000 -> 3.716 | K6: =IF(J6>=Rubric!$C$29,5,IF(J6>=Rubric!$C$30,4,IF(J6>=Rubric!$C$31,3,IF(J6>=Rubric!$C$32,2,1)))) -> 4
A7: W | B7: Water | C7: W03 | D7: Water availability | E7: Water availability refers to the amount of water that is physically present and accessible in a given area over a specified period of time. | F7: Volume of water use | G7: WU15 Water infrastructure upgrades; WU16 Water storage and drought response; WU18 Digitalisation of water management systems; WU19 Sewerage infrastructure | H7: Goal 3: Water (indicative) | I7: =COUNTIF(NBSAP_Commitments!$E:$E,C7) -> 3 | J7: =SUMIF(NBSAP_Commitments!$E:$E,C7,NBSAP_Commitments!$H:$H)/1000000000 -> 2.2 | K7: =IF(J7>=Rubric!$C$29,5,IF(J7>=Rubric!$C$30,4,IF(J7>=Rubric!$C$31,3,IF(J7>=Rubric!$C$32,2,1)))) -> 3
A8: AFF | B8: Agriculture, forestry and fisheries | C8: AFF01 | D8: Sustainable forestry | E8: Sustainable forestry is the management of forests to generate long‑term economic returns while maintaining forest health, productivity, biodiversity, and carbon storage over time. | F8: Other biotic resource extraction (e.g. timber) | G8: FO01 Reforestation / forest regeneration; FO02 Afforestation / large-scale tree planting; FO03 Habitat restoration (incl. peatlands) in forest landscapes; FO04 Sustainable forest management & biodiversity improvement; FO05 Agroforestry systems; FO06 Forestry sector modernisation finance (loans/guarantees/programmes) | H8: Thriving plants and wildlife; sustainable use of nature (indicative) | I8: =COUNTIF(NBSAP_Commitments!$E:$E,C8) -> 2 | J8: =SUMIF(NBSAP_Commitments!$E:$E,C8,NBSAP_Commitments!$H:$H)/1000000000 -> 1.816 | K8: =IF(J8>=Rubric!$C$29,5,IF(J8>=Rubric!$C$30,4,IF(J8>=Rubric!$C$31,3,IF(J8>=Rubric!$C$32,2,1)))) -> 3
A9: AFF | B9: Agriculture, forestry and fisheries | C9: AFF02 | D9: Sustainable agriculture | E9: Sustainable agriculture is food and fibre production that maintains long‑term farm productivity and profitability while protecting soil, water, biodiversity, and resilience to climate and market risks. | F9: Area of land use | G9: FO07 Agri-environment & sustainable farming schemes (payments/eco-schemes); FO08 Soil restoration & regenerative practices; FO09 Ecosystem restoration in agricultural landscapes; FO10 Organic agriculture transition support; FO11 Controlled environment agriculture (greenhouses / vertical farming); FO12 Agro-ecology & digital agriculture R&D; FO13 Genetic resources & agrobiodiversity stewardship | H9: Sustainable use of nature; farming (indicative) | I9: =COUNTIF(NBSAP_Commitments!$E:$E,C9) -> 2 | J9: =SUMIF(NBSAP_Commitments!$E:$E,C9,NBSAP_Commitments!$H:$H)/1000000000 -> 5 | K9: =IF(J9>=Rubric!$C$29,5,IF(J9>=Rubric!$C$30,4,IF(J9>=Rubric!$C$31,3,IF(J9>=Rubric!$C$32,2,1)))) -> 4
A10: AFF | B10: Agriculture, forestry and fisheries | C10: AFF03 | D10: Sustainable fisheries and aquaculture | E10: Sustainable fisheries are fisheries managed so fish stocks remain healthy and economically viable over the long term, avoiding overfishing and minimising ecosystem damage. | F10: Other biotic resource extraction (e.g. fish) | G10: FO14 Sustainable fisheries management plans & governance; FO15 Sustainable/green fishing & aquaculture funding programmes; FO16 Fishing fleet modernisation & new tech/equipment; FO17 Clean technology adoption for fisheries/aquaculture; FO18 Marine protected areas (MPAs) & conservation finance; FO19 Blue economy partnerships & international ocean governance; FO20 Aquaculture growth & investment capital | H10: Sustainable use of nature; marine (indicative) | I10: =COUNTIF(NBSAP_Commitments!$E:$E,C10) -> 1 | J10: =SUMIF(NBSAP_Commitments!$E:$E,C10,NBSAP_Commitments!$H:$H)/1000000000 -> 0.36 | K10: =IF(J10>=Rubric!$C$29,5,IF(J10>=Rubric!$C$30,4,IF(J10>=Rubric!$C$31,3,IF(J10>=Rubric!$C$32,2,1)))) -> 2
A11: UD | B11: Urban development and infrastructure | C11: UD01 | D11: Nature-positive buildings | E11: Designing buildings and construction systems that reduce pressure on ecosystems and actively support biodiversity | F11: Other biotic resource extraction (e.g. timber) | G11: I1 Sustainable materials (certified timber, recycled & bio‑based); I2 Green / nature‑inclusive building standards & certification; I3 Biodiversity features (green roofs/walls, bird‑safe design, pollinator landscaping); I4 SuDS (sustainable drainage systems) & stormwater nature‑based solutions (rain gardens, bioswales, permeable paving) | H11: Thriving plants and wildlife; nature in development (indicative) | I11: =COUNTIF(NBSAP_Commitments!$E:$E,C11) -> 1 | J11: =SUMIF(NBSAP_Commitments!$E:$E,C11,NBSAP_Commitments!$H:$H)/1000000000 -> 0.012 | K11: =IF(J11>=Rubric!$C$29,5,IF(J11>=Rubric!$C$30,4,IF(J11>=Rubric!$C$31,3,IF(J11>=Rubric!$C$32,2,1)))) -> 1
A12: UD | B12: Urban development and infrastructure | C12: UD02 | D12: Green-blue infrastructure, corridors and regeneration | E12: Economic activities that design, restore, and manage interconnected green and water‑based systems to enhance biodiversity, ecosystem connectivity, climate resilience, and nature‑positive urban and infrastructure regeneration. | F12: Area of land use | G12: I5 Biodiversity friendly transmission corridors; I7 Green/blue corridors & ecological connectivity (greenways, habitat corridors); I8 De‑sealing & nature‑positive urban regeneration / public realm upgrades; I9 Green city infrastructure | H12: Thriving plants and wildlife; green infrastructure (indicative) | I12: =COUNTIF(NBSAP_Commitments!$E:$E,C12) -> 0 | J12: =SUMIF(NBSAP_Commitments!$E:$E,C12,NBSAP_Commitments!$H:$H)/1000000000 -> 0 | K12: =IF(J12>=Rubric!$C$29,5,IF(J12>=Rubric!$C$30,4,IF(J12>=Rubric!$C$31,3,IF(J12>=Rubric!$C$32,2,1)))) -> 1
A13: UD | B13: Urban development and infrastructure | C13: UD03 | D13: Land-use change and habitat protection | E13: Economic activities and interventions that prevent, reduce, or reverse the conversion and degradation of natural ecosystems by protecting habitats and influencing how land is allocated, managed, and conserved. | F13: Area of land use | G13: I10 Urban waterways & wetland restoration (incl. floodplain reconnection); I11 Urban greening programmes (parks, pocket parks, micro‑forests, tree canopies); I12 Habitat protection from building permissions/protection from land-use changes | H13: Thriving plants and wildlife; habitat protection (indicative) | I13: =COUNTIF(NBSAP_Commitments!$E:$E,C13) -> 5 | J13: =SUMIF(NBSAP_Commitments!$E:$E,C13,NBSAP_Commitments!$H:$H)/1000000000 -> 15.429 | K13: =IF(J13>=Rubric!$C$29,5,IF(J13>=Rubric!$C$30,4,IF(J13>=Rubric!$C$31,3,IF(J13>=Rubric!$C$32,2,1)))) -> 5
A14: DM | B14: Disaster management and adaptation | C14: DM01 | D14: Risk reduction and prevention | E14: Actions that protect, restore, or sustainably manage biodiversity and ecosystems to reduce the likelihood and intensity of hazards by addressing ecological degradation before risks materialise. | F14: Disturbance | G14: A01 River and coastal flood defences; A02 Flood retention areas and floodplain restoration; A03 Urban drainage upgrades and stormwater tunnels; A04 Landscape restoration to reduce erosion; A05 Drought-resilience water supply infrastructure; A06 Vegetation and fuel-load management; A07 Land-use and forest management to reduce fire severity | H14: Climate adaptation; environmental hazards (indicative) | I14: =COUNTIF(NBSAP_Commitments!$E:$E,C14) -> 6 | J14: =SUMIF(NBSAP_Commitments!$E:$E,C14,NBSAP_Commitments!$H:$H)/1000000000 -> 20.498 | K14: =IF(J14>=Rubric!$C$29,5,IF(J14>=Rubric!$C$30,4,IF(J14>=Rubric!$C$31,3,IF(J14>=Rubric!$C$32,2,1)))) -> 5
A15: DM | B15: Disaster management and adaptation | C15: DM02 | D15: Flood mitigation | E15: Flood mitigation refers to reducing the likelihood and impacts of flooding by working with natural systems—such as wetlands, floodplains, soils, and vegetation—to slow, store, and safely absorb excess water while enhancing ecosystem health. | F15: Disturbance | G15: A08 Flood, drought, heatwave and wildfire early-warning systems; A09 Emergency coordination and crisis communication systems; A10 Heat health warning systems; A15 Flood risk management; A16 Sponge cities for flood reduction | H15: Climate adaptation; environmental hazards (indicative) | I15: =COUNTIF(NBSAP_Commitments!$E:$E,C15) -> 0 | J15: =SUMIF(NBSAP_Commitments!$E:$E,C15,NBSAP_Commitments!$H:$H)/1000000000 -> 0 | K15: =IF(J15>=Rubric!$C$29,5,IF(J15>=Rubric!$C$30,4,IF(J15>=Rubric!$C$31,3,IF(J15>=Rubric!$C$32,2,1)))) -> 1
A16: DM | B16: Disaster management and adaptation | C16: DM03 | D16: Long-term adaptation and resilience | E16: Strategies that enhance the capacity of biodiversity and ecosystems to adapt to long‑term and compounding pressures, enabling them to withstand, recover from, and continue functioning under future environmental change. | F16: Disturbance | G16: A11 Resilience upgrades to existing infrastructure; A12 Design standards to reduce overheating in buildings; A13 Ecosystem-based approaches | H16: Climate adaptation (indicative) | I16: =COUNTIF(NBSAP_Commitments!$E:$E,C16) -> 1 | J16: =SUMIF(NBSAP_Commitments!$E:$E,C16,NBSAP_Commitments!$H:$H)/1000000000 -> 0.015 | K16: =IF(J16>=Rubric!$C$29,5,IF(J16>=Rubric!$C$30,4,IF(J16>=Rubric!$C$31,3,IF(J16>=Rubric!$C$32,2,1)))) -> 1
... A19: P | B19: Pollution and waste | C19: P03 | D19: Air pollution, disturbances & noise pollution | E19: Emissions and physical disturbances arising from human activities—such as airborne pollutants, artificial noise, and other disruptions—that impair air quality and interfere with ecosystem functioning, species behaviour, and biodiversity health. | F19: Emissions of non-GHG air pollutants | G19: PL8 Transport noise reduction; PL9 Aviation noise mitigation; PL10 Urban noise monitoring & mitigation; PL11 Development of technologies to reduce air pollution | H19: Clean air (indicative) | I19: =COUNTIF(NBSAP_Commitments!$E:$E,C19) -> 2 | J19: =SUMIF(NBSAP_Commitments!$E:$E,C19,NBSAP_Commitments!$H:$H)/1000000000 -> 0.598 | K19: =IF(J19>=Rubric!$C$29,5,IF(J19>=Rubric!$C$30,4,IF(J19>=Rubric!$C$31,3,IF(J19>=Rubric!$C$32,2,1)))) -> 2
H20: Total | I20: =SUM(I5:I19) -> 34 | J20: =SUM(J5:J19) -> 60.038

Sheet NBSAP_Commitments
A1: UK NBSAP commitments (EY workbook, Market_Examples, Country_ID = GBR)
A2: Assigned to the sub-theme that owns each sub-market in the taxonomy. Values in original GBP (not the USD-converted columns).
A4: Example_ID | B4: Sub_Market_ID | C4: Sub-market | D4: Market_ID (as tagged) | E4: SubTheme_ID (taxonomy parent) | F4: Tag consistent? | G4: Commitment | H4: Value (GBP) | I4: Financing method | J4: Financial product | K4: Source
A5: M48 | B5: FO03 | C5: Habitat restoration (incl. peatlands) in forest landscapes | D5: AFF01 | E5: AFF01 | F5: =IF(D5=E5,"Yes","No – see Data_QA") -> Yes | G5: Incentivise the planting of high-quality woodlands and trees outside of woodland between 2026 to 2027 and 2029 to 2030 | H5: 816000000 | I5: Grant financing | J5: Restricted funds | K5: NBSAP
A6: M49 | B6: FO01 | C6: Reforestation / forest regeneration | D6: AFF01 | E6: AFF01 | F6: =IF(D6=E6,"Yes","No – see Data_QA") -> Yes | G6: Investments into new forests will see millions of trees planted in the years ahead as part of a wider commitment to tree planting and support to the forestry sector | H6: 1000000000 | I6: Grant financing | J6: Restricted funds | K6: NBSAP
A7: M50 | B7: FO07 | C7: Agri-environment & sustainable farming schemes (payments/eco-schemes) | D7: AFF02 | E7: AFF02 | F7: =IF(D7=E7,"Yes","No – see Data_QA") -> Yes | G7: Allocated to sustainable farming and Environmental Land Management schemes | H7: 2700000000 | I7: Grant financing | J7: Restricted funds | K7: NBSAP
A8: M51 | B8: FO07 | C8: Agri-environment & sustainable farming schemes (payments/eco-schemes) | D8: AFF02 | E8: AFF02 | F8: =IF(D8=E8,"Yes","No – see Data_QA") -> Yes | G8: Farming and countryside programme to farmers and land managers | H8: 2300000000 | I8: Grant financing | J8: Restricted funds | K8: NBSAP
A9: M52 | B9: FO16 | C9: Fishing fleet modernisation & new tech/equipment | D9: AFF03 | E9: AFF03 | F9: =IF(D9=E9,"Yes","No – see Data_QA") -> Yes | G9: Investment in fishing and coastal growth fund (2025) over 12 years for modernising UK fishing fleet, new tech and equipment | H9: 360000000 | I9: Grant financing | J9: Restricted funds | K9: NBSAP
A10: M01 | B10: A03 | C10: Urban drainage upgrades and stormwater tunnels | D10: DM01 | E10: DM01 | F10: =IF(D10=E10,"Yes","No – see Data_QA") -> Yes | G10: Investment into storm overflows to deliver 50% reduction in spills | H10: 10000000000 | I10: Equity and debt finance | J10: Term debt and equity | K10: NBSAP
A11: M09 | B11: A03 | C11: Urban drainage upgrades and stormwater tunnels | D11: DM01 | E11: DM01 | F11: =IF(D11=E11,"Yes","No – see Data_QA") -> Yes | G11: Reduce storm overflow discharges | H11: 2240000000 | I11: Equity and debt finance | J11: Term debt and equity | K11: Plan for Water: our integrated plan for delivering clean and plentiful water - GOV.UK
A12: M143 | B12: A01 | C12: River and coastal flood defences | D12: DM02 | E12: DM01 | F12: =IF(D12=E12,"Yes","No – see Data_QA") -> No – see Data_QA | G12: Nature-based solutions are a key part of our approach to mitigating flood risk and coastal erosion. We will invest in natural flood management over 10 years | H12: 300000000 | I12: Grant financing | J12: Restricted funds | K12: NBSAP
A13: M144 | B13: A02 | C13: Flood retention areas and floodplain restoration | D13: DM02 | E13: DM01 | F13: =IF(D13=E13,"Yes","No – see Data_QA") -> No – see Data_QA | G13: We inherited flood assets in their worst condition on record, with 92% of the Environment Agency’s 38,000 high consequence assets at required condition, which is why an additional amount is being re-prioritised into asset maintenance , ensuring an additional 14,500 properties will have their expected level of protection maintained or restored | H13: 108000000 | I13: Grant financing | J13: Restricted funds | K13: NBSAP
A14: M145 | B14: A01 | C14: River and coastal flood defences | D14: DM02 | E14: DM01 | F14: =IF(D14=E14,"Yes","No – see Data_QA") -> No – see Data_QA | G14: Better protect 52,000 properties from flooding by March 2026 | H14: 2650000000 | I14: Grant financing | J14: Restricted funds | K14: Flood and coastal erosion risk management: an investment plan for 2021 to 2027 - GOV.UK
A15: M146 | B15: A01 | C15: River and coastal flood defences | D15: DM02 | E15: DM01 | F15: =IF(D15=E15,"Yes","No – see Data_QA") -> No – see Data_QA | G15: New 6-year flood and coastal defence investment programme in England between 2021 and 2027 | H15: 5200000000 | I15: Grant financing | J15: Restricted funds | K15: Flood and coastal erosion risk management: an investment plan for 2021 to 2027 - GOV.UK
A16: M142 | B16: A11 | C16: Resilience upgrades to existing infrastructure | D16: DM03 | E16: DM03 | F16: =IF(D16=E16,"Yes","No – see Data_QA") -> Yes | G16: Create GBP DEFRA-UKRI joint research initiative to support adaptation action with research innovation | H16: 15000000 | I16: Grant financing | J16: Restricted funds | K16: NBSAP
... A38: M12 | B38: WU15 | C38: Water infrastructure upgrades | D38: W03 | E38: W03 | F38: =IF(D38=E38,"Yes","No – see Data_QA") -> Yes | G38: New water company infrastructure Delivery to start in the next 2 years – reducing the number of spills from storm overflows, nutrient pollution, and increasing water supply | H38: 1600000000 | I38: Debt financing | J38: Term debt | K38: Plan for Water: our integrated plan for delivering clean and plentiful water - GOV.UK
G39: Total | H39: =SUM(H5:H38) -> 60038000000

Sheet Evidence_Log
A1: Evidence log
A2: All quotes checked word-for-word against the source PDFs (25 words or fewer).
A4: Evidence_ID | B4: Source_ID | C4: Page/Section | D4: Verbatim quote | E4: Evidence type | F4: Scope | G4: Summary
A5: EV-001 | B5: SRC-01 | C5: p.4 | D5: As part of a ten-year partnership, Lloyds Banking Group has supported Soil Association Exchange | E5: Partnership | F5: Value chain / portfolio | G5: Ten-year partnership supporting a standardised farm environmental impact measurement and advice approach.
A6: EV-002 | B6: SRC-01 | C6: p.4 | D6: To date, it has spanned 238,494 hectares of farmland across 685 farms | E6: Performance metric | F6: Value chain / portfolio | G6: Coverage of 685 farms; six areas incl. soil, carbon, biodiversity and water; 4,000+ recommendations and 750+ actions.
A7: EV-003 | B7: SRC-01 | C7: p.4 | D7: Lloyds Banking Group has donated £250,000 split between three nature recovery projects | E7: Partnership | F7: Products and services | G7: Founding business partner of Projects for Nature (England); philanthropic support for nature recovery.
A8: EV-004 | B8: SRC-01 | C8: p.4 | D8: aims to deliver nature-based solutions to reduce flood risk, restore nature and mitigate climate change | E8: Partnership | F8: Products and services | G8: Resilient Glenderamackin (Cumbria), a Projects for Nature project using natural flood management.
A9: EV-005 | B9: SRC-01 | C9: p.7 | D9: Biodiversity Net Gain (BNG) became mandatory in England in February 2024 to ensure that all new developments deliver a 10% measurable positive impact on biodiversity | E9: Disclosure | F9: External driver | G9: Regulatory driver for development finance (housing, commercial real estate).
A10: EV-006 | B10: SRC-01 | C10: p.7 | D10: Natural England has developed a Green Infrastructure Framework to help increase the amount of green cover to 40% in urban residential areas | E10: Disclosure | F10: External driver | G10: Policy driver for urban green infrastructure.
A11: EV-007 | B11: SRC-01 | C11: p.9 | D11: for every £1 invested in peatland restoration, the average expected returns are estimated to be at least £4.62 in economic and social benefits | E11: Disclosure | F11: Products and services | G11: LBG cites cost-benefit evidence for NbS (also woodland £2.79, saltmarsh £1.31).
A12: EV-008 | B12: SRC-01 | C12: p.13 | D12: the finance gap to meet the UK’s nature related outcomes in the UK is £56 billion | E12: Disclosure | F12: External driver | G12: UK nature finance gap over the next decade (Green Finance Institute, cited by LBG).
A13: EV-009 | B13: SRC-01 | C13: p.13 | D13: Financial drivers include an increasing focus on climate and nature related financial risks via the Taskforce for Nature based Financial Disclosures (TNFD) | E13: Disclosure | F13: External driver | G13: LBG recognises TNFD as a driver; no LBG TNFD disclosure in sources reviewed.
A14: EV-010 | B14: SRC-01 | C14: p.14 | D14: Mandate Schedule 3 of Flood and Water Management Act in England. | E14: Policy | F14: Products and services | G14: LBG policy ask: mandatory SuDS for new development.
A15: EV-011 | B15: SRC-01 | C15: p.14 | D15: Unblock flows of green finance to UK farmers, and work with private actors to overcome the financial barriers to greater uptake of sustainable practices. | E15: Policy | F15: Value chain / portfolio | G15: LBG policy ask: blended finance for sustainable farming.
... A37: EV-033 | B37: SRC-02 | C37: p.21 | D37: integrating physical climate risks into lending, investment and insurance decisions | E37: Policy | F37: Products and services | G37: LBG recommendation for the finance sector; no LBG nature-risk methodology disclosed.

Sheet NBSAP_Mapping
A1: Mapping of evidence to taxonomy and UK NBSAP
A2: Evidence class: Client action (what LBG has done) | Client position (what LBG says or advocates) | External driver (regulation/market context cited by LBG). XC = cross-cutting.
A4: Evidence_ID | B4: Source_ID | C4: Evidence class | D4: Primary SubTheme_ID | E4: Primary Sub_Market_ID | F4: Secondary SubTheme_ID | G4: UK NBSAP link | H4: Mapping strength | I4: Rationale
A5: EV-001 | B5: =INDEX(Evidence_Log!$B:$B,MATCH(A5,Evidence_Log!$A:$A,0)) -> SRC-01 | C5: Client action | D5: AFF02 | E5: FO08 | F5: W02 | G5: =IFERROR(INDEX(Taxonomy!$H:$H,MATCH(D5,Taxonomy!$C:$C,0)),"Cross-cutting") -> Sustainable use of nature; farming (indicative) | H5: Direct | I5: Farm environmental baseline and advice directly supports regenerative practice.
A6: EV-002 | B6: =INDEX(Evidence_Log!$B:$B,MATCH(A6,Evidence_Log!$A:$A,0)) -> SRC-01 | C6: Client action | D6: AFF02 | E6: FO08 | F6: W02 | G6: =IFERROR(INDEX(Taxonomy!$H:$H,MATCH(D6,Taxonomy!$C:$C,0)),"Cross-cutting") -> Sustainable use of nature; farming (indicative) | H6: Direct | I6: Quantified reach across 685 farms incl. soil, biodiversity and water.
A7: EV-003 | B7: =INDEX(Evidence_Log!$B:$B,MATCH(A7,Evidence_Log!$A:$A,0)) -> SRC-01 | C7: Client action | D7: UD03 | E7: I12 | F7: AFF02 | G7: =IFERROR(INDEX(Taxonomy!$H:$H,MATCH(D7,Taxonomy!$C:$C,0)),"Cross-cutting") -> Thriving plants and wildlife; habitat protection (indicative) | H7: Indirect | I7: Philanthropic support for nature recovery; not a financing activity.
A8: EV-004 | B8: =INDEX(Evidence_Log!$B:$B,MATCH(A8,Evidence_Log!$A:$A,0)) -> SRC-01 | C8: Client action | D8: DM01 | E8: A02 | F8: DM03 | G8: =IFERROR(INDEX(Taxonomy!$H:$H,MATCH(D8,Taxonomy!$C:$C,0)),"Cross-cutting") -> Climate adaptation; environmental hazards (indicative) | H8: Direct | I8: Natural flood management: river re-meandering, wetlands, tree planting.
A9: EV-005 | B9: =INDEX(Evidence_Log!$B:$B,MATCH(A9,Evidence_Log!$A:$A,0)) -> SRC-01 | C9: External driver | D9: UD03 | E9: I12 | F9: UD01 | G9: =IFERROR(INDEX(Taxonomy!$H:$H,MATCH(D9,Taxonomy!$C:$C,0)),"Cross-cutting") -> Thriving plants and wildlife; habitat protection (indicative) | H9: Direct | I9: BNG mandates habitat outcomes for new development.
A10: EV-006 | B10: =INDEX(Evidence_Log!$B:$B,MATCH(A10,Evidence_Log!$A:$A,0)) -> SRC-01 | C10: External driver | D10: UD02 | E10: I9 | F10: UD03 | G10: =IFERROR(INDEX(Taxonomy!$H:$H,MATCH(D10,Taxonomy!$C:$C,0)),"Cross-cutting") -> Thriving plants and wildlife; green infrastructure (indicative) | H10: Direct | I10: Green cover target for urban areas.
A11: EV-007 | B11: =INDEX(Evidence_Log!$B:$B,MATCH(A11,Evidence_Log!$A:$A,0)) -> SRC-01 | C11: Client position | D11: W02 | E11: WU14 | F11: AFF01 | G11: =IFERROR(INDEX(Taxonomy!$H:$H,MATCH(D11,Taxonomy!$C:$C,0)),"Cross-cutting") -> Goal 3: Water (indicative) | H11: Indirect | I11: Cost-benefit evidence for peatland and woodland; no financing linked.
A12: EV-008 | B12: =INDEX(Evidence_Log!$B:$B,MATCH(A12,Evidence_Log!$A:$A,0)) -> SRC-01 | C12: External driver | D12: XC | E12: — | F12: — | G12: =IFERROR(INDEX(Taxonomy!$H:$H,MATCH(D12,Taxonomy!$C:$C,0)),"Cross-cutting") -> Cross-cutting | H12: Indirect | I12: Cross-cutting UK nature finance gap.
A13: EV-009 | B13: =INDEX(Evidence_Log!$B:$B,MATCH(A13,Evidence_Log!$A:$A,0)) -> SRC-01 | C13: External driver | D13: XC | E13: — | F13: — | G13: =IFERROR(INDEX(Taxonomy!$H:$H,MATCH(D13,Taxonomy!$C:$C,0)),"Cross-cutting") -> Cross-cutting | H13: Indirect | I13: Cross-cutting disclosure driver.
A14: EV-010 | B14: =INDEX(Evidence_Log!$B:$B,MATCH(A14,Evidence_Log!$A:$A,0)) -> SRC-01 | C14: Client position | D14: UD01 | E14: I4 | F14: DM02 | G14: =IFERROR(INDEX(Taxonomy!$H:$H,MATCH(D14,Taxonomy!$C:$C,0)),"Cross-cutting") -> Thriving plants and wildlife; nature in development (indicative) | H14: Direct | I14: SuDS in new buildings and developments.
A15: EV-011 | B15: =INDEX(Evidence_Log!$B:$B,MATCH(A15,Evidence_Log!$A:$A,0)) -> SRC-01 | C15: Client position | D15: AFF02 | E15: FO07 | F15: — | G15: =IFERROR(INDEX(Taxonomy!$H:$H,MATCH(D15,Taxonomy!$C:$C,0)),"Cross-cutting") -> Sustainable use of nature; farming (indicative) | H15: Direct | I15: Green and blended finance for sustainable farming.
A16: EV-012 | B16: =INDEX(Evidence_Log!$B:$B,MATCH(A16,Evidence_Log!$A:$A,0)) -> SRC-01 | C16: Client position | D16: UD01 | E16: I4 | F16: W02 | G16: =IFERROR(INDEX(Taxonomy!$H:$H,MATCH(D16,Taxonomy!$C:$C,0)),"Cross-cutting") -> Thriving plants and wildlife; nature in development (indicative) | H16: Direct | I16: NbSuDS on premises improve drainage and water quality.
... A37: EV-033 | B37: =INDEX(Evidence_Log!$B:$B,MATCH(A37,Evidence_Log!$A:$A,0)) -> SRC-02 | C37: Client position | D37: DM02 | E37: A15 | F37: DM01 | G37: =IFERROR(INDEX(Taxonomy!$H:$H,MATCH(D37,Taxonomy!$C:$C,0)),"Cross-cutting") -> Climate adaptation; environmental hazards (indicative) | H37: Indirect | I37: Advocates physical-risk integration in lending.

Sheet Rubric
A1: Scoring rubric
A4: Code | B4: Criterion | C4: Weight | D4: What a 5 / 1 means
A5: C1 | B5: Materiality to client | C5: 0.3 | D5: 5 = core business line or large portfolio share; 1 = no identifiable relevance in sources
A6: C2 | B6: Action gap | C6: 0.25 | D6: 5 = material but no disclosed action; 3 = commitments without targets; 1 = quantified targets with reported progress. Capped at 2 when C1 is 2 or less.
A7: C3 | B7: NBSAP emphasis | C7: 0.2 | D7: From number of UK NBSAP commitments in the EY workbook (bands below)
A8: C4 | B8: Regulatory and market momentum | C8: 0.15 | D8: 5 = mandatory requirements in force or confirmed; 1 = none identified in sources
A9: C5 | B9: Market opportunity | C9: 0.1 | D9: From UK NBSAP commitment value (£bn) in the EY workbook (bands below)
B10: Total weight | C10: =SUM(C5:C9) -> 1
A12: Tiers
B13: High: score at least | C13: 4
B14: Medium: score at least | C14: 3
B15: Low: below Medium threshold | C15: —
D16: Tie-break: higher C1, then higher C2, then more client evidence items.
A18: Confidence
D19: High: 3+ client evidence items (action or position) from 2+ sources with at least one Direct mapping. Medium: 1+ client items otherwise. Low: no client evidence.
A21: C3 bands | B21: UK NBSAP commitments (no.) at least | C21: Score
B22: 4 | C22: 5
B23: 3 | C23: 4
B24: 2 | C24: 3
B25: 1 | C25: 2
B26: 0 | C26: 1
A28: C5 bands | B28: UK NBSAP commitments (£bn) at least (score)
B29: Score 5 | C29: 10
B30: Score 4 | C30: 3
B31: Score 3 | C31: 1
B32: Score 2 | C32: 0.1
B33: Score 1 | C33: below £0.1bn

Sheet Scoring
A1: Scoring and ranking
A2: Blue = analyst judgement (C1, C2, C4). C3 and C5 calculate from Taxonomy. Change weights or bands in Rubric.
A4: Rank | B4: SubTheme_ID | C4: Theme | D4: Sub-theme | E4: C1 Materiality | F4: C2 Action gap | G4: C3 NBSAP emphasis | H4: C4 Regulatory & market momentum | I4: C5 Market opportunity | J4: Weighted score | K4: Tier | L4: Confidence | M4: Client evidence (no.) | N4: Client sources (no.) | O4: Direct mappings (no.) | P4: Evidence_IDs | Q4: Rationale | R4: Sort key
A5: =RANK(R5,$R$5:$R$19) -> 1 | B5: DM01 | C5: =Taxonomy!B14 -> Disaster management and adaptation | D5: =Taxonomy!D14 -> Risk reduction and prevention | E5: 5 | F5: 3 | G5: =IF(Taxonomy!I14>=Rubric!$B$22,Rubric!$C$22,IF(Taxonomy!I14>=Rubric!$B$23,Rubric!$C$23,IF(Taxonomy!I14>=Rubric!$B$24,Rubric!$C$24,IF(Taxonomy!I14>=Rubric!$B$25,Rubric!$C$25,Rubric!$C$26)))) -> 5 | H5: 5 | I5: =Taxonomy!K14 -> 5 | J5: =ROUND(E5*Rubric!$C$5+F5*Rubric!$C$6+G5*Rubric!$C$7+H5*Rubric!$C$8+I5*Rubric!$C$9+0.000000001,1) -> 4.5 | K5: =IF(J5>=Rubric!$C$13,"High",IF(J5>=Rubric!$C$14,"Medium","Low")) -> High | L5: =IF(M5=0,"Low",IF(AND(M5>=3,N5>=2,O5>=1),"High","Medium")) -> Medium | M5: =COUNTIFS(NBSAP_Mapping!$D$5:$D$37,B5,NBSAP_Mapping!$C$5:$C$37,"<>External driver") -> 1 | N5: =(COUNTIFS(NBSAP_Mapping!$D$5:$D$37,B5,NBSAP_Mapping!$C$5:$C$37,"<>External driver",NBSAP_Mapping!$B$5:$B$37,"SRC-01")>0)+(COUNTIFS(NBSAP_Mapping!$D$5:$D$37,B5,NBSAP_Mapping!$C$5:$C$37,"<>External driver",NBSAP_Mapping!$B$5:$B$37,"SRC-02")>0) -> 1 | O5: =COUNTIFS(NBSAP_Mapping!$D$5:$D$37,B5,NBSAP_Mapping!$C$5:$C$37,"<>External driver",NBSAP_Mapping!$H$5:$H$37,"Direct") -> 1 | P5: EV-004, EV-020, EV-023 (sec.), EV-025 (sec.) | Q5: C1: flood and drought resilience is the core of Built to Last; Cleve Hill and HARP financed. C2: deal-level action within group £100bn target, no adaptation-specific target. C4: PRA SS5/25, £7.9bn flood pipeline. | R5: =J5*10000+E5*100+F5*10+MIN(M5,9)-ROW()/100000 -> 45531
A6: =RANK(R6,$R$5:$R$19) -> 2 | B6: UD03 | C6: =Taxonomy!B13 -> Urban development and infrastructure | D6: =Taxonomy!D13 -> Land-use change and habitat protection | E6: 3 | F6: 4 | G6: =IF(Taxonomy!I13>=Rubric!$B$22,Rubric!$C$22,IF(Taxonomy!I13>=Rubric!$B$23,Rubric!$C$23,IF(Taxonomy!I13>=Rubric!$B$24,Rubric!$C$24,IF(Taxonomy!I13>=Rubric!$B$25,Rubric!$C$25,Rubric!$C$26)))) -> 5 | H6: 5 | I6: =Taxonomy!K13 -> 5 | J6: =ROUND(E6*Rubric!$C$5+F6*Rubric!$C$6+G6*Rubric!$C$7+H6*Rubric!$C$8+I6*Rubric!$C$9+0.000000001,1) -> 4.2 | K6: =IF(J6>=Rubric!$C$13,"High",IF(J6>=Rubric!$C$14,"Medium","Low")) -> High | L6: =IF(M6=0,"Low",IF(AND(M6>=3,N6>=2,O6>=1),"High","Medium")) -> High | M6: =COUNTIFS(NBSAP_Mapping!$D$5:$D$37,B6,NBSAP_Mapping!$C$5:$C$37,"<>External driver") -> 3 | N6: =(COUNTIFS(NBSAP_Mapping!$D$5:$D$37,B6,NBSAP_Mapping!$C$5:$C$37,"<>External driver",NBSAP_Mapping!$B$5:$B$37,"SRC-01")>0)+(COUNTIFS(NBSAP_Mapping!$D$5:$D$37,B6,NBSAP_Mapping!$C$5:$C$37,"<>External driver",NBSAP_Mapping!$B$5:$B$37,"SRC-02")>0) -> 2 | O6: =COUNTIFS(NBSAP_Mapping!$D$5:$D$37,B6,NBSAP_Mapping!$C$5:$C$37,"<>External driver",NBSAP_Mapping!$H$5:$H$37,"Direct") -> 2 | P6: EV-003, EV-005, EV-021, EV-024, EV-026 | Q6: C1: project-level BNG (10%, 65%) and £250k Projects for Nature. C2: no portfolio habitat or BNG commitment. C4: BNG mandatory since Feb 2024. | R6: =J6*10000+E6*100+F6*10+MIN(M6,9)-ROW()/100000 -> 42343
A7: =RANK(R7,$R$5:$R$19) -> 3 | B7: W03 | C7: =Taxonomy!B7 -> Water | D7: =Taxonomy!D7 -> Water availability | E7: 5 | F7: 3 | G7: =IF(Taxonomy!I7>=Rubric!$B$22,Rubric!$C$22,IF(Taxonomy!I7>=Rubric!$B$23,Rubric!$C$23,IF(Taxonomy!I7>=Rubric!$B$24,Rubric!$C$24,IF(Taxonomy!I7>=Rubric!$B$25,Rubric!$C$25,Rubric!$C$26)))) -> 4 | H7: 4 | I7: =Taxonomy!K7 -> 3 | J7: =ROUND(E7*Rubric!$C$5+F7*Rubric!$C$6+G7*Rubric!$C$7+H7*Rubric!$C$8+I7*Rubric!$C$9+0.000000001,1) -> 4 | K7: =IF(J7>=Rubric!$C$13,"High",IF(J7>=Rubric!$C$14,"Medium","Low")) -> High | L7: =IF(M7=0,"Low",IF(AND(M7>=3,N7>=2,O7>=1),"High","Medium")) -> Medium | M7: =COUNTIFS(NBSAP_Mapping!$D$5:$D$37,B7,NBSAP_Mapping!$C$5:$C$37,"<>External driver") -> 1 | N7: =(COUNTIFS(NBSAP_Mapping!$D$5:$D$37,B7,NBSAP_Mapping!$C$5:$C$37,"<>External driver",NBSAP_Mapping!$B$5:$B$37,"SRC-01")>0)+(COUNTIFS(NBSAP_Mapping!$D$5:$D$37,B7,NBSAP_Mapping!$C$5:$C$37,"<>External driver",NBSAP_Mapping!$B$5:$B$37,"SRC-02")>0) -> 1 | O7: =COUNTIFS(NBSAP_Mapping!$D$5:$D$37,B7,NBSAP_Mapping!$C$5:$C$37,"<>External driver",NBSAP_Mapping!$H$5:$H$37,"Direct") -> 1 | P7: EV-019, EV-023, EV-024 (sec.) | Q7: C1: £120m long-term debt to HARP; drought highlighted as material. C2: deal-level action, no water target. C4: Ofwat direct procurement, 2026 drought. | R7: =J7*10000+E7*100+F7*10+MIN(M7,9)-ROW()/100000 -> 40531
A8: =RANK(R8,$R$5:$R$19) -> 4 | B8: AFF02 | C8: =Taxonomy!B9 -> Agriculture, forestry and fisheries | D8: =Taxonomy!D9 -> Sustainable agriculture | E8: 5 | F8: 3 | G8: =IF(Taxonomy!I9>=Rubric!$B$22,Rubric!$C$22,IF(Taxonomy!I9>=Rubric!$B$23,Rubric!$C$23,IF(Taxonomy!I9>=Rubric!$B$24,Rubric!$C$24,IF(Taxonomy!I9>=Rubric!$B$25,Rubric!$C$25,Rubric!$C$26)))) -> 3 | H8: 4 | I8: =Taxonomy!K9 -> 4 | J8: =ROUND(E8*Rubric!$C$5+F8*Rubric!$C$6+G8*Rubric!$C$7+H8*Rubric!$C$8+I8*Rubric!$C$9+0.000000001,1) -> 3.9 | K8: =IF(J8>=Rubric!$C$13,"High",IF(J8>=Rubric!$C$14,"Medium","Low")) -> Medium | L8: =IF(M8=0,"Low",IF(AND(M8>=3,N8>=2,O8>=1),"High","Medium")) -> Medium | M8: =COUNTIFS(NBSAP_Mapping!$D$5:$D$37,B8,NBSAP_Mapping!$C$5:$C$37,"<>External driver") -> 3 | N8: =(COUNTIFS(NBSAP_Mapping!$D$5:$D$37,B8,NBSAP_Mapping!$C$5:$C$37,"<>External driver",NBSAP_Mapping!$B$5:$B$37,"SRC-01")>0)+(COUNTIFS(NBSAP_Mapping!$D$5:$D$37,B8,NBSAP_Mapping!$C$5:$C$37,"<>External driver",NBSAP_Mapping!$B$5:$B$37,"SRC-02")>0) -> 1 | O8: =COUNTIFS(NBSAP_Mapping!$D$5:$D$37,B8,NBSAP_Mapping!$C$5:$C$37,"<>External driver",NBSAP_Mapping!$H$5:$H$37,"Direct") -> 3 | P8: EV-001, EV-002, EV-011 | Q8: C1: ten-year Soil Association Exchange partnership (685 farms); LBG calls for green finance to farmers. C2: reach metrics but no portfolio target. C4: land management schemes, nature markets. | R8: =J8*10000+E8*100+F8*10+MIN(M8,9)-ROW()/100000 -> 39533
A9: =RANK(R9,$R$5:$R$19) -> 5 | B9: W02 | C9: =Taxonomy!B6 -> Water | D9: =Taxonomy!D6 -> Water quality | E9: 3 | F9: 4 | G9: =IF(Taxonomy!I6>=Rubric!$B$22,Rubric!$C$22,IF(Taxonomy!I6>=Rubric!$B$23,Rubric!$C$23,IF(Taxonomy!I6>=Rubric!$B$24,Rubric!$C$24,IF(Taxonomy!I6>=Rubric!$B$25,Rubric!$C$25,Rubric!$C$26)))) -> 5 | H9: 4 | I9: =Taxonomy!K6 -> 4 | J9: =ROUND(E9*Rubric!$C$5+F9*Rubric!$C$6+G9*Rubric!$C$7+H9*Rubric!$C$8+I9*Rubric!$C$9+0.000000001,1) -> 3.9 | K9: =IF(J9>=Rubric!$C$13,"High",IF(J9>=Rubric!$C$14,"Medium","Low")) -> Medium | L9: =IF(M9=0,"Low",IF(AND(M9>=3,N9>=2,O9>=1),"High","Medium")) -> Medium | M9: =COUNTIFS(NBSAP_Mapping!$D$5:$D$37,B9,NBSAP_Mapping!$C$5:$C$37,"<>External driver") -> 3 | N9: =(COUNTIFS(NBSAP_Mapping!$D$5:$D$37,B9,NBSAP_Mapping!$C$5:$C$37,"<>External driver",NBSAP_Mapping!$B$5:$B$37,"SRC-01")>0)+(COUNTIFS(NBSAP_Mapping!$D$5:$D$37,B9,NBSAP_Mapping!$C$5:$C$37,"<>External driver",NBSAP_Mapping!$B$5:$B$37,"SRC-02")>0) -> 1 | O9: =COUNTIFS(NBSAP_Mapping!$D$5:$D$37,B9,NBSAP_Mapping!$C$5:$C$37,"<>External driver",NBSAP_Mapping!$H$5:$H$37,"Direct") -> 0 | P9: EV-007, EV-012 (sec.), EV-014, EV-015 | Q9: C1: water quality central to LBG NbS paper but no linked financing. C2: thought leadership only. C4: nutrient neutrality and phosphorus standards cited. | R9: =J9*10000+E9*100+F9*10+MIN(M9,9)-ROW()/100000 -> 39343
A10: =RANK(R10,$R$5:$R$19) -> 6 | B10: W01 | C10: =Taxonomy!B5 -> Water | D10: =Taxonomy!D5 -> Water usage | E10: 3 | F10: 4 | G10: =IF(Taxonomy!I5>=Rubric!$B$22,Rubric!$C$22,IF(Taxonomy!I5>=Rubric!$B$23,Rubric!$C$23,IF(Taxonomy!I5>=Rubric!$B$24,Rubric!$C$24,IF(Taxonomy!I5>=Rubric!$B$25,Rubric!$C$25,Rubric!$C$26)))) -> 5 | H10: 3 | I10: =Taxonomy!K5 -> 2 | J10: =ROUND(E10*Rubric!$C$5+F10*Rubric!$C$6+G10*Rubric!$C$7+H10*Rubric!$C$8+I10*Rubric!$C$9+0.000000001,1) -> 3.6 | K10: =IF(J10>=Rubric!$C$13,"High",IF(J10>=Rubric!$C$14,"Medium","Low")) -> Medium | L10: =IF(M10=0,"Low",IF(AND(M10>=3,N10>=2,O10>=1),"High","Medium")) -> Low | M10: =COUNTIFS(NBSAP_Mapping!$D$5:$D$37,B10,NBSAP_Mapping!$C$5:$C$37,"<>External driver") -> 0 | N10: =(COUNTIFS(NBSAP_Mapping!$D$5:$D$37,B10,NBSAP_Mapping!$C$5:$C$37,"<>External driver",NBSAP_Mapping!$B$5:$B$37,"SRC-01")>0)+(COUNTIFS(NBSAP_Mapping!$D$5:$D$37,B10,NBSAP_Mapping!$C$5:$C$37,"<>External driver",NBSAP_Mapping!$B$5:$B$37,"SRC-02")>0) -> 0 | O10: =COUNTIFS(NBSAP_Mapping!$D$5:$D$37,B10,NBSAP_Mapping!$C$5:$C$37,"<>External driver",NBSAP_Mapping!$H$5:$H$37,"Direct") -> 0 | P10: EV-028 (sec.), EV-031 | Q10: C1: water efficiency appears only in university fund criteria (EY view: moderate relevance to utility and real estate lending). C2: no commitments. C4: CCC leakage priority. | R10: =J10*10000+E10*100+F10*10+MIN(M10,9)-ROW()/100000 -> 36340
A11: =RANK(R11,$R$5:$R$19) -> 7 | B11: DM03 | C11: =Taxonomy!B16 -> Disaster management and adaptation | D11: =Taxonomy!D16 -> Long-term adaptation and resilience | E11: 5 | F11: 3 | G11: =IF(Taxonomy!I16>=Rubric!$B$22,Rubric!$C$22,IF(Taxonomy!I16>=Rubric!$B$23,Rubric!$C$23,IF(Taxonomy!I16>=Rubric!$B$24,Rubric!$C$24,IF(Taxonomy!I16>=Rubric!$B$25,Rubric!$C$25,Rubric!$C$26)))) -> 2 | H11: 5 | I11: =Taxonomy!K16 -> 1 | J11: =ROUND(E11*Rubric!$C$5+F11*Rubric!$C$6+G11*Rubric!$C$7+H11*Rubric!$C$8+I11*Rubric!$C$9+0.000000001,1) -> 3.5 | K11: =IF(J11>=Rubric!$C$13,"High",IF(J11>=Rubric!$C$14,"Medium","Low")) -> Medium | L11: =IF(M11=0,"Low",IF(AND(M11>=3,N11>=2,O11>=1),"High","Medium")) -> Medium | M11: =COUNTIFS(NBSAP_Mapping!$D$5:$D$37,B11,NBSAP_Mapping!$C$5:$C$37,"<>External driver") -> 3 | N11: =(COUNTIFS(NBSAP_Mapping!$D$5:$D$37,B11,NBSAP_Mapping!$C$5:$C$37,"<>External driver",NBSAP_Mapping!$B$5:$B$37,"SRC-01")>0)+(COUNTIFS(NBSAP_Mapping!$D$5:$D$37,B11,NBSAP_Mapping!$C$5:$C$37,"<>External driver",NBSAP_Mapping!$B$5:$B$37,"SRC-02")>0) -> 1 | O11: =COUNTIFS(NBSAP_Mapping!$D$5:$D$37,B11,NBSAP_Mapping!$C$5:$C$37,"<>External driver",NBSAP_Mapping!$H$5:$H$37,"Direct") -> 3 | P11: EV-018, EV-025, EV-027, EV-029 | Q11: C1: £500m retrofit with heat and flood criteria; Cleve Hill resilient design. C2: product exists, no adaptation target. C4: CCC Well Adapted UK, PRA SS5/25. | R11: =J11*10000+E11*100+F11*10+MIN(M11,9)-ROW()/100000 -> 35533
A12: =RANK(R12,$R$5:$R$19) -> 8 | B12: DM02 | C12: =Taxonomy!B15 -> Disaster management and adaptation | D12: =Taxonomy!D15 -> Flood mitigation | E12: 4 | F12: 4 | G12: =IF(Taxonomy!I15>=Rubric!$B$22,Rubric!$C$22,IF(Taxonomy!I15>=Rubric!$B$23,Rubric!$C$23,IF(Taxonomy!I15>=Rubric!$B$24,Rubric!$C$24,IF(Taxonomy!I15>=Rubric!$B$25,Rubric!$C$25,Rubric!$C$26)))) -> 1 | H12: 5 | I12: =Taxonomy!K15 -> 1 | J12: =ROUND(E12*Rubric!$C$5+F12*Rubric!$C$6+G12*Rubric!$C$7+H12*Rubric!$C$8+I12*Rubric!$C$9+0.000000001,1) -> 3.3 | K12: =IF(J12>=Rubric!$C$13,"High",IF(J12>=Rubric!$C$14,"Medium","Low")) -> Medium | L12: =IF(M12=0,"Low",IF(AND(M12>=3,N12>=2,O12>=1),"High","Medium")) -> Medium | M12: =COUNTIFS(NBSAP_Mapping!$D$5:$D$37,B12,NBSAP_Mapping!$C$5:$C$37,"<>External driver") -> 1 | N12: =(COUNTIFS(NBSAP_Mapping!$D$5:$D$37,B12,NBSAP_Mapping!$C$5:$C$37,"<>External driver",NBSAP_Mapping!$B$5:$B$37,"SRC-01")>0)+(COUNTIFS(NBSAP_Mapping!$D$5:$D$37,B12,NBSAP_Mapping!$C$5:$C$37,"<>External driver",NBSAP_Mapping!$B$5:$B$37,"SRC-02")>0) -> 1 | O12: =COUNTIFS(NBSAP_Mapping!$D$5:$D$37,B12,NBSAP_Mapping!$C$5:$C$37,"<>External driver",NBSAP_Mapping!$H$5:$H$37,"Direct") -> 0 | P12: EV-022, EV-033 | Q12: C1: flood risk material to mortgage and property lending (EY view). C2: advocates physical-risk integration, no approach disclosed. C4: PRA SS5/25. | R12: =J12*10000+E12*100+F12*10+MIN(M12,9)-ROW()/100000 -> 33441
A13: =RANK(R13,$R$5:$R$19) -> 9 | B13: UD01 | C13: =Taxonomy!B11 -> Urban development and infrastructure | D13: =Taxonomy!D11 -> Nature-positive buildings | E13: 4 | F13: 3 | G13: =IF(Taxonomy!I11>=Rubric!$B$22,Rubric!$C$22,IF(Taxonomy!I11>=Rubric!$B$23,Rubric!$C$23,IF(Taxonomy!I11>=Rubric!$B$24,Rubric!$C$24,IF(Taxonomy!I11>=Rubric!$B$25,Rubric!$C$25,Rubric!$C$26)))) -> 2 | H13: 4 | I13: =Taxonomy!K11 -> 1 | J13: =ROUND(E13*Rubric!$C$5+F13*Rubric!$C$6+G13*Rubric!$C$7+H13*Rubric!$C$8+I13*Rubric!$C$9+0.000000001,1) -> 3.1 | K13: =IF(J13>=Rubric!$C$13,"High",IF(J13>=Rubric!$C$14,"Medium","Low")) -> Medium | L13: =IF(M13=0,"Low",IF(AND(M13>=3,N13>=2,O13>=1),"High","Medium")) -> High | M13: =COUNTIFS(NBSAP_Mapping!$D$5:$D$37,B13,NBSAP_Mapping!$C$5:$C$37,"<>External driver") -> 3 | N13: =(COUNTIFS(NBSAP_Mapping!$D$5:$D$37,B13,NBSAP_Mapping!$C$5:$C$37,"<>External driver",NBSAP_Mapping!$B$5:$B$37,"SRC-01")>0)+(COUNTIFS(NBSAP_Mapping!$D$5:$D$37,B13,NBSAP_Mapping!$C$5:$C$37,"<>External driver",NBSAP_Mapping!$B$5:$B$37,"SRC-02")>0) -> 2 | O13: =COUNTIFS(NBSAP_Mapping!$D$5:$D$37,B13,NBSAP_Mapping!$C$5:$C$37,"<>External driver",NBSAP_Mapping!$H$5:$H$37,"Direct") -> 3 | P13: EV-010, EV-012, EV-028 | Q13: C1: £500m retrofit lending with biodiversity criteria; SuDS advocacy. C2: product criteria, no target. C4: BNG mandatory; Schedule 3 not yet mandated. | R13: =J13*10000+E13*100+F13*10+MIN(M13,9)-ROW()/100000 -> 31433
A14: =RANK(R14,$R$5:$R$19) -> 10 | B14: UD02 | C14: =Taxonomy!B12 -> Urban development and infrastructure | D14: =Taxonomy!D12 -> Green-blue infrastructure, corridors and regeneration | E14: 3 | F14: 4 | G14: =IF(Taxonomy!I12>=Rubric!$B$22,Rubric!$C$22,IF(Taxonomy!I12>=Rubric!$B$23,Rubric!$C$23,IF(Taxonomy!I12>=Rubric!$B$24,Rubric!$C$24,IF(Taxonomy!I12>=Rubric!$B$25,Rubric!$C$25,Rubric!$C$26)))) -> 1 | H14: 4 | I14: =Taxonomy!K12 -> 1 | J14: =ROUND(E14*Rubric!$C$5+F14*Rubric!$C$6+G14*Rubric!$C$7+H14*Rubric!$C$8+I14*Rubric!$C$9+0.000000001,1) -> 2.8 | K14: =IF(J14>=Rubric!$C$13,"High",IF(J14>=Rubric!$C$14,"Medium","Low")) -> Low | L14: =IF(M14=0,"Low",IF(AND(M14>=3,N14>=2,O14>=1),"High","Medium")) -> Low | M14: =COUNTIFS(NBSAP_Mapping!$D$5:$D$37,B14,NBSAP_Mapping!$C$5:$C$37,"<>External driver") -> 0 | N14: =(COUNTIFS(NBSAP_Mapping!$D$5:$D$37,B14,NBSAP_Mapping!$C$5:$C$37,"<>External driver",NBSAP_Mapping!$B$5:$B$37,"SRC-01")>0)+(COUNTIFS(NBSAP_Mapping!$D$5:$D$37,B14,NBSAP_Mapping!$C$5:$C$37,"<>External driver",NBSAP_Mapping!$B$5:$B$37,"SRC-02")>0) -> 0 | O14: =COUNTIFS(NBSAP_Mapping!$D$5:$D$37,B14,NBSAP_Mapping!$C$5:$C$37,"<>External driver",NBSAP_Mapping!$H$5:$H$37,"Direct") -> 0 | P14: EV-006, EV-026 (sec.) | Q14: C1: urban green-blue infrastructure discussed extensively; limited financing evidence. C2: advocacy only. C4: Green Infrastructure Framework, BNG. | R14: =J14*10000+E14*100+F14*10+MIN(M14,9)-ROW()/100000 -> 28340
A15: =RANK(R15,$R$5:$R$19) -> 11 | B15: AFF01 | C15: =Taxonomy!B8 -> Agriculture, forestry and fisheries | D15: =Taxonomy!D8 -> Sustainable forestry | E15: 2 | F15: 2 | G15: =IF(Taxonomy!I8>=Rubric!$B$22,Rubric!$C$22,IF(Taxonomy!I8>=Rubric!$B$23,Rubric!$C$23,IF(Taxonomy!I8>=Rubric!$B$24,Rubric!$C$24,IF(Taxonomy!I8>=Rubric!$B$25,Rubric!$C$25,Rubric!$C$26)))) -> 3 | H15: 3 | I15: =Taxonomy!K8 -> 3 | J15: =ROUND(E15*Rubric!$C$5+F15*Rubric!$C$6+G15*Rubric!$C$7+H15*Rubric!$C$8+I15*Rubric!$C$9+0.000000001,1) -> 2.5 | K15: =IF(J15>=Rubric!$C$13,"High",IF(J15>=Rubric!$C$14,"Medium","Low")) -> Low | L15: =IF(M15=0,"Low",IF(AND(M15>=3,N15>=2,O15>=1),"High","Medium")) -> Low | M15: =COUNTIFS(NBSAP_Mapping!$D$5:$D$37,B15,NBSAP_Mapping!$C$5:$C$37,"<>External driver") -> 0 | N15: =(COUNTIFS(NBSAP_Mapping!$D$5:$D$37,B15,NBSAP_Mapping!$C$5:$C$37,"<>External driver",NBSAP_Mapping!$B$5:$B$37,"SRC-01")>0)+(COUNTIFS(NBSAP_Mapping!$D$5:$D$37,B15,NBSAP_Mapping!$C$5:$C$37,"<>External driver",NBSAP_Mapping!$B$5:$B$37,"SRC-02")>0) -> 0 | O15: =COUNTIFS(NBSAP_Mapping!$D$5:$D$37,B15,NBSAP_Mapping!$C$5:$C$37,"<>External driver",NBSAP_Mapping!$H$5:$H$37,"Direct") -> 0 | P15: EV-007 (sec.) | Q15: C1: woodland and hedgerow benefits cited only. C2: capped (C1 ≤ 2). C4: Nature Markets Framework. | R15: =J15*10000+E15*100+F15*10+MIN(M15,9)-ROW()/100000 -> 25220
A16: =RANK(R16,$R$5:$R$19) -> 12 | B16: P03 | C16: =Taxonomy!B19 -> Pollution and waste | D16: =Taxonomy!D19 -> Air pollution, disturbances & noise pollution | E16: 2 | F16: 2 | G16: =IF(Taxonomy!I19>=Rubric!$B$22,Rubric!$C$22,IF(Taxonomy!I19>=Rubric!$B$23,Rubric!$C$23,IF(Taxonomy!I19>=Rubric!$B$24,Rubric!$C$24,IF(Taxonomy!I19>=Rubric!$B$25,Rubric!$C$25,Rubric!$C$26)))) -> 3 | H16: 2 | I16: =Taxonomy!K19 -> 2 | J16: =ROUND(E16*Rubric!$C$5+F16*Rubric!$C$6+G16*Rubric!$C$7+H16*Rubric!$C$8+I16*Rubric!$C$9+0.000000001,1) -> 2.2 | K16: =IF(J16>=Rubric!$C$13,"High",IF(J16>=Rubric!$C$14,"Medium","Low")) -> Low | L16: =IF(M16=0,"Low",IF(AND(M16>=3,N16>=2,O16>=1),"High","Medium")) -> Low | M16: =COUNTIFS(NBSAP_Mapping!$D$5:$D$37,B16,NBSAP_Mapping!$C$5:$C$37,"<>External driver") -> 0 | N16: =(COUNTIFS(NBSAP_Mapping!$D$5:$D$37,B16,NBSAP_Mapping!$C$5:$C$37,"<>External driver",NBSAP_Mapping!$B$5:$B$37,"SRC-01")>0)+(COUNTIFS(NBSAP_Mapping!$D$5:$D$37,B16,NBSAP_Mapping!$C$5:$C$37,"<>External driver",NBSAP_Mapping!$B$5:$B$37,"SRC-02")>0) -> 0 | O16: =COUNTIFS(NBSAP_Mapping!$D$5:$D$37,B16,NBSAP_Mapping!$C$5:$C$37,"<>External driver",NBSAP_Mapping!$H$5:$H$37,"Direct") -> 0 | P16: — | Q16: C1: air quality cited only as an NbS co-benefit. C2: capped (C1 ≤ 2). C4: limited drivers in sources. | R16: =J16*10000+E16*100+F16*10+MIN(M16,9)-ROW()/100000 -> 22220
A17: =RANK(R17,$R$5:$R$19) -> 13 | B17: P02 | C17: =Taxonomy!B18 -> Pollution and waste | D17: =Taxonomy!D18 -> Waste & circular economy | E17: 1 | F17: 1 | G17: =IF(Taxonomy!I18>=Rubric!$B$22,Rubric!$C$22,IF(Taxonomy!I18>=Rubric!$B$23,Rubric!$C$23,IF(Taxonomy!I18>=Rubric!$B$24,Rubric!$C$24,IF(Taxonomy!I18>=Rubric!$B$25,Rubric!$C$25,Rubric!$C$26)))) -> 2 | H17: 1 | I17: =Taxonomy!K18 -> 5 | J17: =ROUND(E17*Rubric!$C$5+F17*Rubric!$C$6+G17*Rubric!$C$7+H17*Rubric!$C$8+I17*Rubric!$C$9+0.000000001,1) -> 1.6 | K17: =IF(J17>=Rubric!$C$13,"High",IF(J17>=Rubric!$C$14,"Medium","Low")) -> Low | L17: =IF(M17=0,"Low",IF(AND(M17>=3,N17>=2,O17>=1),"High","Medium")) -> Low | M17: =COUNTIFS(NBSAP_Mapping!$D$5:$D$37,B17,NBSAP_Mapping!$C$5:$C$37,"<>External driver") -> 0 | N17: =(COUNTIFS(NBSAP_Mapping!$D$5:$D$37,B17,NBSAP_Mapping!$C$5:$C$37,"<>External driver",NBSAP_Mapping!$B$5:$B$37,"SRC-01")>0)+(COUNTIFS(NBSAP_Mapping!$D$5:$D$37,B17,NBSAP_Mapping!$C$5:$C$37,"<>External driver",NBSAP_Mapping!$B$5:$B$37,"SRC-02")>0) -> 0 | O17: =COUNTIFS(NBSAP_Mapping!$D$5:$D$37,B17,NBSAP_Mapping!$C$5:$C$37,"<>External driver",NBSAP_Mapping!$H$5:$H$37,"Direct") -> 0 | P17: — | Q17: No evidence identified in public sources reviewed. | R17: =J17*10000+E17*100+F17*10+MIN(M17,9)-ROW()/100000 -> 16110
A18: =RANK(R18,$R$5:$R$19) -> 14 | B18: AFF03 | C18: =Taxonomy!B10 -> Agriculture, forestry and fisheries | D18: =Taxonomy!D10 -> Sustainable fisheries and aquaculture | E18: 1 | F18: 1 | G18: =IF(Taxonomy!I10>=Rubric!$B$22,Rubric!$C$22,IF(Taxonomy!I10>=Rubric!$B$23,Rubric!$C$23,IF(Taxonomy!I10>=Rubric!$B$24,Rubric!$C$24,IF(Taxonomy!I10>=Rubric!$B$25,Rubric!$C$25,Rubric!$C$26)))) -> 2 | H18: 1 | I18: =Taxonomy!K10 -> 2 | J18: =ROUND(E18*Rubric!$C$5+F18*Rubric!$C$6+G18*Rubric!$C$7+H18*Rubric!$C$8+I18*Rubric!$C$9+0.000000001,1) -> 1.3 | K18: =IF(J18>=Rubric!$C$13,"High",IF(J18>=Rubric!$C$14,"Medium","Low")) -> Low | L18: =IF(M18=0,"Low",IF(AND(M18>=3,N18>=2,O18>=1),"High","Medium")) -> Low | M18: =COUNTIFS(NBSAP_Mapping!$D$5:$D$37,B18,NBSAP_Mapping!$C$5:$C$37,"<>External driver") -> 0 | N18: =(COUNTIFS(NBSAP_Mapping!$D$5:$D$37,B18,NBSAP_Mapping!$C$5:$C$37,"<>External driver",NBSAP_Mapping!$B$5:$B$37,"SRC-01")>0)+(COUNTIFS(NBSAP_Mapping!$D$5:$D$37,B18,NBSAP_Mapping!$C$5:$C$37,"<>External driver",NBSAP_Mapping!$B$5:$B$37,"SRC-02")>0) -> 0 | O18: =COUNTIFS(NBSAP_Mapping!$D$5:$D$37,B18,NBSAP_Mapping!$C$5:$C$37,"<>External driver",NBSAP_Mapping!$H$5:$H$37,"Direct") -> 0 | P18: — | Q18: No evidence identified in public sources reviewed. | R18: =J18*10000+E18*100+F18*10+MIN(M18,9)-ROW()/100000 -> 13110
A19: =RANK(R19,$R$5:$R$19) -> 15 | B19: P01 | C19: =Taxonomy!B17 -> Pollution and waste | D19: =Taxonomy!D17 -> Innovation in sustainable packaging and biodegradable materials | E19: 1 | F19: 1 | G19: =IF(Taxonomy!I17>=Rubric!$B$22,Rubric!$C$22,IF(Taxonomy!I17>=Rubric!$B$23,Rubric!$C$23,IF(Taxonomy!I17>=Rubric!$B$24,Rubric!$C$24,IF(Taxonomy!I17>=Rubric!$B$25,Rubric!$C$25,Rubric!$C$26)))) -> 2 | H19: 1 | I19: =Taxonomy!K17 -> 2 | J19: =ROUND(E19*Rubric!$C$5+F19*Rubric!$C$6+G19*Rubric!$C$7+H19*Rubric!$C$8+I19*Rubric!$C$9+0.000000001,1) -> 1.3 | K19: =IF(J19>=Rubric!$C$13,"High",IF(J19>=Rubric!$C$14,"Medium","Low")) -> Low | L19: =IF(M19=0,"Low",IF(AND(M19>=3,N19>=2,O19>=1),"High","Medium")) -> Low | M19: =COUNTIFS(NBSAP_Mapping!$D$5:$D$37,B19,NBSAP_Mapping!$C$5:$C$37,"<>External driver") -> 0 | N19: =(COUNTIFS(NBSAP_Mapping!$D$5:$D$37,B19,NBSAP_Mapping!$C$5:$C$37,"<>External driver",NBSAP_Mapping!$B$5:$B$37,"SRC-01")>0)+(COUNTIFS(NBSAP_Mapping!$D$5:$D$37,B19,NBSAP_Mapping!$C$5:$C$37,"<>External driver",NBSAP_Mapping!$B$5:$B$37,"SRC-02")>0) -> 0 | O19: =COUNTIFS(NBSAP_Mapping!$D$5:$D$37,B19,NBSAP_Mapping!$C$5:$C$37,"<>External driver",NBSAP_Mapping!$H$5:$H$37,"Direct") -> 0 | P19: — | Q19: No evidence identified in public sources reviewed. | R19: =J19*10000+E19*100+F19*10+MIN(M19,9)-ROW()/100000 -> 13110

Sheet Data_QA
A1: Data quality observations on the EY NBSAP workbook (UK rows)
A4: # | B4: Tab | C4: Issue | D4: Example | E4: Impact | F4: Suggested fix
A5: 1 | B5: Market_Size | C5: Double currency conversion: Market_Size_Value (labelled GBP) equals the sum of USD values, which is then multiplied by 1.32 again. | D5: UKW01: Market_Size_Value 229,680,000 = USD sum; GBP commitments total £174m; USD Value shows $303m. | E5: UK market sizes in USD overstated by c.32%. | F5: Sum original GBP values, then convert once.
A6: 2 | B6: Market_Size | C6: UKDM02 shows GBP value 0 but USD value 27,057,000,000 (equal to DM01). | D6: UKDM02 row. | E6: Flood mitigation appears as a $27bn market in USD outputs. | F6: Correct formula reference for DM02.
A7: 3 | B7: Market_Examples | C7: Market_ID tag does not match the parent market of the Sub_Market_ID. | D7: M143, M144, M145, M146 (A01/A02 belong to DM01, tagged DM02); M123 (I2 belongs to UD01, tagged UD02); M13 (WU14 belongs to W02, tagged W03). | E7: Sub-theme totals differ depending on which field is used. | F7: Align tags to taxonomy; this analysis uses the sub-market parent.
A8: 4 | B8: Market_Examples | C8: Flood defence programmes classified under UD03 / I10 (urban waterways and wetland restoration). | D8: M120 (£4.2bn) and M121 (£10.5bn) flood and coastal programmes. | E8: Inflates UD03 (habitat protection) and understates DM01. | F8: Consider re-tagging to DM01 / A01.
A9: 5 | B9: Market_Examples | C9: Possible overlapping commitments. | D9: M145 (£2.65bn, 52,000 properties) appears to sit within M146 (£5.2bn FCERM programme 2021–27); M01 and M09 both cover storm overflows. | E9: Totals may double count. | F9: Flag overlaps; treat totals as indicative.
A10: 6 | B10: NBSAP_Markets | C10: Only UK W01 has an NBSAP target reference and policy signal strength. | D10: All other UK markets blank. | E10: NBSAP goal links for 14 of 15 sub-themes are indicative. | F10: Complete NBSAP_Target_Ref for all UK markets from EIP 2025.
A11: 7 | B11: Countries | C11: United Kingdom region recorded as "EU". | D11: GBR row. | E11: Regional filters in Power BI may misclassify the UK. | F11: Change to "Europe (non-EU)" or similar.
A12: 8 | B12: Market_Size | C12: Year stored as number in some rows and text in others. | D12: UKW01 = 2025 (number); UKW02 = "2025" (text). | E12: Power BI filtering by year may miss rows. | F12: Standardise data type.

Sheet QA_Log
A1: Quality assurance checklist
A4: # | B4: Check | C4: Result | D4: Formula / note
A5: 1 | B5: All 15 sub-themes in the Taxonomy appear in Scoring | C5: =IF(COUNTA(Scoring!B5:B19)=COUNTA(Taxonomy!C5:C19),"Pass","Fail") -> Pass | D5: Formula
A6: 2 | B6: Every evidence item has a source, page and quote | C6: =IF(COUNTBLANK(Evidence_Log!B5:D37)=0,"Pass","Fail") -> Pass | D6: Formula
A7: 3 | B7: Quotes are verbatim and 25 words or fewer | C7: Pass | D7: Checked with a script against the PDF text layer
A8: 4 | B8: Weights total 100% | C8: =IF(ABS(Rubric!C10-1)<0.0001,"Pass","Fail") -> Pass | D8: Formula
A9: 5 | B9: C2 cap respected (C2 ≤ 2 where C1 ≤ 2) | C9: =IF(SUMPRODUCT((Scoring!E5:E19<=2)*(Scoring!F5:F19>2))=0,"Pass","Fail") -> Pass | D9: Formula
A10: 6 | B10: Every evidence item is mapped | C10: =IF(COUNTA(NBSAP_Mapping!A5:A37)=COUNTA(Evidence_Log!A5:A37),"Pass","Fail") -> Pass | D10: Formula
A11: 7 | B11: Ranks are unique | C11: =IF(SUMPRODUCT(1/COUNTIF(Scoring!A5:A19,Scoring!A5:A19))=COUNTA(Scoring!A5:A19),"Pass","Fail") -> Pass | D11: Formula
A12: 8 | B12: Slide figures match workbook | C12: Pass | D12: Checked manually after deck build
A13: 9 | B13: UK English, neutral tone; interpretation labelled "EY view" | C13: Pass | D13: Manual review
A14: 10 | B14: Low-confidence scores flagged | C14: =COUNTIF(Scoring!L5:L19,"Low")&" sub-themes Low confidence – flagged on slide 2" -> 7 sub-themes Low confidence – flagged on slide 2 | D14: Formula
