Workbook

Sheet README
A1: Nature Opportunity Master Template
A2: Purpose | B2: Reusable workbook for any client and any country in the EY NBSAP Nature Sizing workbook. Copilot (or an analyst) fills the blue input tabs; Excel calculates scores, tiers, ranks and confidence.
A3: How to start a new client | B3: 1) Save a copy named <Client>_<Country>_Nature_Mapping.xlsx. 2) Inputs: set Client, Country_ID (e.g. GBR, FRA, CAN), sector, as-at date. 3) Refresh NBSAP_Commitments and Taxonomy from the latest EY NBSAP workbook if it has changed. 4) Paste Copilot outputs into Sources, Client_Exposure, Evidence_Log, NBSAP_Mapping and the blue columns of Scoring. 5) Check QA_Log is all Pass.
A4: What makes it country-agnostic | B4: NBSAP commitments are filtered by Inputs!Country_ID. Values use the USD column from the EY workbook. C5 (market opportunity) is scored on relative rank within the chosen country, so currency and economy size do not distort scores.
A5: Colour legend | B5: Blue text = input (paste or type). Black = formula. Green = pulled from another tab. Yellow fill = check before use. Rows marked EXAMPLE are illustrative – delete them.
A6: Tabs | B6: Inputs | Sources | Client_Exposure | Taxonomy | Sub_Markets | NBSAP_Commitments | NBSAP_Targets | Evidence_Log | NBSAP_Mapping | Rubric | Scoring | QA_Log
A7: Known data caveats | B7: EY NBSAP workbook: some Market_ID tags differ from the sub-market parent; this template always uses the sub-market parent. Commitment values are indicative (timeframes vary, some overlap). Only some countries have NBSAP_Target_Ref populated – complete NBSAP_Targets for the country you are running.

Sheet Inputs
A1: Inputs
A4: Field | B4: Value | C4: Note
A5: Client | B5: [Client name] | C5: Full name and short name, e.g. Lloyds Banking Group (LBG)
A6: Country_ID | B6: GBR | C6: ISO-3 code from the Countries tab of the EY NBSAP workbook
A7: Country name | B7: =IFERROR(INDEX(Countries!B:B,MATCH(B6,Countries!A:A,0)),"Unknown Country_ID") | C7: Formula
A8: NBSAP document | B8: =IFERROR(INDEX(Countries!F:F,MATCH(B6,Countries!A:A,0)),"") | C8: Formula
A9: Sector | B9: [e.g. Banking and financial services]
A10: Audience | B10: Internal (EY partner) | C10: Internal or External
A11: As-at date | B11: [DD/MM/YYYY]
A12: Prepared by | B12: EY CCaSS | C12: No individual names in client outputs

Sheet Countries
A1: Countries (from EY NBSAP workbook)
A4: Country_ID | B4: Country_Name | C4: Region | D4: NBSAP_Status | E4: NBSAP_Year | F4: NBSAP document
A5: GBR | B5: United Kingdom | C5: EU | D5: Published | E5: 2025 | F5: Environmental Improvement Plan 2025
A6: CAN | B6: Canada | C6: North America | D6: Published | E6: 2024 | F6: Canada's 2030 Nature Strategy
A7: QAT | B7: Qatar | C7: Middle East | D7: Outdated | E7: 2015 | F7: CBD Strategy and Action Plan - Qatar (English version)
A8: SAU | B8: Saudi Arabia | C8: Middle East | D8: Published | E8: 2025 | F8: Comprehensive Framework for Biodiversity
A9: ARE | B9: United Arab Emirates | C9: Middle East | D9: Published | E9: 2024 | F9: Framework for Biodiversity Strategy
A10: FRA | B10: France | C10: EU | D10: Published | E10: 2023 | F10: National Biodiversity Strategy 2030
A11: ESP | B11: Spain | C11: EU | D11: Published | E11: 2022 | F11: State Strategic Plan for Natural Heritage and Biodiversity to 2030
A12: DEU | B12: Germany | C12: EU | D12: Published | E12: 2025 | F12: National Biodiversity Strategy 2030
A13: IRL | B13: Ireland | C13: EU | D13: Published | E13: 2023 | F13: National Biodiversity Action Plan 2023-2030
A14: PRT | B14: Portugal | C14: EU | D14: Not published | E14: N/A | F14: N/A
A15: ITA | B15: Italy | C15: EU | D15: Published | E15: 2024 | F15: Italina Biodiversity Strategy 2030

Sheet Sources
A1: Sources
A4: Source_ID | B4: Title | C4: Publisher | D4: Year | E4: Type | F4: Location / URL | G4: Date accessed | H4: Included (Y/N) | I4: Reason / note
A5: SRC-01 | B5: [Client] Sustainability Report 2025 | C5: [Client] | D5: 2026 | E5: Annual / sustainability report | F5: [file name] | G5: [date] | H5: Y | I5: EXAMPLE – delete

Sheet Client_Exposure
A1: Client portfolio exposure by sector
A2: Copy figures exactly as disclosed (e.g. TNFD priority sectors, concentration of exposure tables). Do not estimate.
A4: Source_ID | B4: Sector (as disclosed) | C4: Sub-sector | D4: Exposure (m, reporting currency) | E4: Currency | F4: Nature priority (as disclosed) | G4: % of total exposure | H4: Linked SubTheme_IDs | I4: Reference (tab/page)
A5: SRC-02 | B5: Agriculture, forestry and fishing | C5: Agriculture | D5: 6695 | E5: GBP | F5: Yes | G5: 0.01 | H5: AFF02 | I5: Data sheet tab 18 – EXAMPLE

Sheet Sub_Markets
A1: Sub-markets (from EY NBSAP workbook)
A4: Sub_Market_ID | B4: SubTheme_ID (parent) | C4: Sub-market | D4: Description | E4: Field of play
A5: WU01 | B5: W01 | C5: AgTech and irrigation efficiency | D5: Technologies and practices that improve water use efficiency in agriculture, including precision irrigation (e.g. drip and micro‑irrigation), soil‑moisture sensing, digital farm management tools, and automated control systems, with the objective of reducing water withdrawals while maintaining or increasing crop yields. | E5: Technology development and R&D
A6: WU02 | B6: W01 | C6: Leak detection systems | D6: Hardware and software solutions used to identify, locate, and quantify water losses in distribution and transmission networks, including acoustic sensors, pressure and flow monitoring, satellite and drone detection, and AI‑based analytics, aimed at reducing non‑revenue water. | E6: Technology development and R&D
A7: WU03 | B7: W01 | C7: Smart meters | D7: Digitally enabled water meters that provide real‑time or near‑real‑time measurement of water consumption, enabling remote reading, demand management, leak detection at the customer level, and data‑driven pricing and conservation strategies. | E7: Technology development and R&D
A8: WU04 | B8: W01 | C8: Water cycle digitalisation | D8: The application of digital technologies across the entire urban and industrial water cycle—from abstraction and treatment to distribution, wastewater, and reuse—using sensors, data platforms, AI, and digital twins to optimise performance, resilience, and regulatory compliance. | E8: Technology development and R&D
A9: WU07 | B9: W01 | C9: Industrial process water efficiency | D9: Technologies and operational improvements that reduce water use, losses, and contamination in industrial processes, including closed‑loop systems, water recycling, advanced cooling, and process optimisation to lower operational costs and environmental impacts. | E9: Technology development and R&D
A10: WU08 | B10: W01 | C10: Nuclear cooling water efficiency | D10: Specialised systems and technologies that optimise water use for nuclear power plant cooling, including closed‑cycle cooling, cooling towers, advanced heat exchange systems, and water reuse, aimed at reducing abstraction pressures and thermal impacts on water bodies. | E10: Technology development and R&D
A11: WU09 | B11: W02 | C11: Wastewater treatment | D11: Physical, chemical, and biological processes used to remove pollutants from wastewater before discharge or reuse, encompassing primary, secondary, and tertiary treatment, nutrient removal, and advanced treatment technologies for emerging contaminants. | E11: Business transition
A12: WU10 | B12: W02 | C12: Desalination | D12: Technologies that convert saline or brackish water into freshwater, primarily through reverse osmosis and thermal processes, to augment water supply in water‑stressed regions, often integrated with energy‑efficiency and brine‑management solutions. | E12: Technology development and R&D
A13: WU11 | B13: W02 | C13: Water body conservation | D13: Activities and investments aimed at protecting and restoring the ecological status of rivers, lakes, and reservoirs, including pollution reduction, habitat restoration, flow management, and monitoring to maintain water quality and ecosystem services. | E13: Protection & restoration
A14: WU12 | B14: W02 | C14: Marine and coastal area protection | D14: Measures to protect marine and coastal ecosystems from pollution, erosion, and climate impacts, including wastewater outfall management, coastal habitat restoration, nature‑based solutions, and marine spatial planning to safeguard biodiversity and coastal resilience. | E14: Protection & restoration
A15: WU13 | B15: W02 | C15: Groundwater abstraction | D15: Infrastructure, monitoring, and management systems associated with the extraction of groundwater resources, including wells, pumps, metering, and regulatory controls, designed to ensure sustainable withdrawal and protect aquifer integrity. | E15: Business transition
... A77: PL11 | B77: P03 | C77: Development of technologies to reduce air pollution | D77: Innovation and deployment of technologies that lower emissions of harmful air pollutants from industrial, transport, and energy sources. | E77: Technology development and R&D

Sheet Taxonomy
A1: Taxonomy and country NBSAP signal
A2: Columns G–K recalculate when Inputs!Country_ID changes. Theme names inferred from codes – confirm.
A4: Theme_ID | B4: Theme | C4: SubTheme_ID | D4: Sub-theme | E4: Definition | F4: ENCORE theme | G4: NBSAP commitments (no.) – selected country | H4: NBSAP commitments (USD bn) – selected country | I4: Relative rank (0–1) | J4: C3 NBSAP emphasis | K4: C5 Market opportunity | L4: NBSAP target link (selected country)
A5: W | B5: Water | C5: W01 | D5: Water usage | E5: Ensuring a sustainable supply of water to homes, the public and businesses | F5: Volume of water use | G5: =COUNTIFS(NBSAP_Commitments!$G$5:$G$1000,C5,NBSAP_Commitments!$B$5:$B$1000,Inputs!$B$6) | H5: =SUMIFS(NBSAP_Commitments!$J$5:$J$1000,NBSAP_Commitments!$G$5:$G$1000,C5,NBSAP_Commitments!$B$5:$B$1000,Inputs!$B$6)/1000000000 | I5: =IF(H5<=0,0,PERCENTRANK($H$5:$H$19,H5)) | J5: =IF(G5>=Rubric!$B$22,5,IF(G5>=Rubric!$B$23,4,IF(G5>=Rubric!$B$24,3,IF(G5>=Rubric!$B$25,2,1)))) | K5: =IF(H5<=0,1,IF(I5>=Rubric!$B$29,5,IF(I5>=Rubric!$B$30,4,IF(I5>=Rubric!$B$31,3,IF(I5>=Rubric!$B$32,2,1))))) | L5: =IFERROR(INDEX(NBSAP_Targets!$C:$C,MATCH(1,INDEX((NBSAP_Targets!$A$5:$A$500=Inputs!$B$6)*(NBSAP_Targets!$B$5:$B$500=C5),0),0)+4),"[to confirm]")
A6: W | B6: Water | C6: W02 | D6: Water quality | E6: Water quality refers to the chemical, physical, and biological characteristics of water, assessed in relation to its suitability for a specific use, such as drinking, ecosystem support, agriculture, industry, or recreation. | F6: Emissions of toxic pollutants to water and soil | G6: =COUNTIFS(NBSAP_Commitments!$G$5:$G$1000,C6,NBSAP_Commitments!$B$5:$B$1000,Inputs!$B$6) | H6: =SUMIFS(NBSAP_Commitments!$J$5:$J$1000,NBSAP_Commitments!$G$5:$G$1000,C6,NBSAP_Commitments!$B$5:$B$1000,Inputs!$B$6)/1000000000 | I6: =IF(H6<=0,0,PERCENTRANK($H$5:$H$19,H6)) | J6: =IF(G6>=Rubric!$B$22,5,IF(G6>=Rubric!$B$23,4,IF(G6>=Rubric!$B$24,3,IF(G6>=Rubric!$B$25,2,1)))) | K6: =IF(H6<=0,1,IF(I6>=Rubric!$B$29,5,IF(I6>=Rubric!$B$30,4,IF(I6>=Rubric!$B$31,3,IF(I6>=Rubric!$B$32,2,1))))) | L6: =IFERROR(INDEX(NBSAP_Targets!$C:$C,MATCH(1,INDEX((NBSAP_Targets!$A$5:$A$500=Inputs!$B$6)*(NBSAP_Targets!$B$5:$B$500=C6),0),0)+4),"[to confirm]")
A7: W | B7: Water | C7: W03 | D7: Water availability | E7: Water availability refers to the amount of water that is physically present and accessible in a given area over a specified period of time. | F7: Volume of water use | G7: =COUNTIFS(NBSAP_Commitments!$G$5:$G$1000,C7,NBSAP_Commitments!$B$5:$B$1000,Inputs!$B$6) | H7: =SUMIFS(NBSAP_Commitments!$J$5:$J$1000,NBSAP_Commitments!$G$5:$G$1000,C7,NBSAP_Commitments!$B$5:$B$1000,Inputs!$B$6)/1000000000 | I7: =IF(H7<=0,0,PERCENTRANK($H$5:$H$19,H7)) | J7: =IF(G7>=Rubric!$B$22,5,IF(G7>=Rubric!$B$23,4,IF(G7>=Rubric!$B$24,3,IF(G7>=Rubric!$B$25,2,1)))) | K7: =IF(H7<=0,1,IF(I7>=Rubric!$B$29,5,IF(I7>=Rubric!$B$30,4,IF(I7>=Rubric!$B$31,3,IF(I7>=Rubric!$B$32,2,1))))) | L7: =IFERROR(INDEX(NBSAP_Targets!$C:$C,MATCH(1,INDEX((NBSAP_Targets!$A$5:$A$500=Inputs!$B$6)*(NBSAP_Targets!$B$5:$B$500=C7),0),0)+4),"[to confirm]")
A8: AFF | B8: Agriculture, forestry and fisheries | C8: AFF01 | D8: Sustainable forestry | E8: Sustainable forestry is the management of forests to generate long‑term economic returns while maintaining forest health, productivity, biodiversity, and carbon storage over time. | F8: Other biotic resource extraction (e.g. timber) | G8: =COUNTIFS(NBSAP_Commitments!$G$5:$G$1000,C8,NBSAP_Commitments!$B$5:$B$1000,Inputs!$B$6) | H8: =SUMIFS(NBSAP_Commitments!$J$5:$J$1000,NBSAP_Commitments!$G$5:$G$1000,C8,NBSAP_Commitments!$B$5:$B$1000,Inputs!$B$6)/1000000000 | I8: =IF(H8<=0,0,PERCENTRANK($H$5:$H$19,H8)) | J8: =IF(G8>=Rubric!$B$22,5,IF(G8>=Rubric!$B$23,4,IF(G8>=Rubric!$B$24,3,IF(G8>=Rubric!$B$25,2,1)))) | K8: =IF(H8<=0,1,IF(I8>=Rubric!$B$29,5,IF(I8>=Rubric!$B$30,4,IF(I8>=Rubric!$B$31,3,IF(I8>=Rubric!$B$32,2,1))))) | L8: =IFERROR(INDEX(NBSAP_Targets!$C:$C,MATCH(1,INDEX((NBSAP_Targets!$A$5:$A$500=Inputs!$B$6)*(NBSAP_Targets!$B$5:$B$500=C8),0),0)+4),"[to confirm]")
A9: AFF | B9: Agriculture, forestry and fisheries | C9: AFF02 | D9: Sustainable agriculture | E9: Sustainable agriculture is food and fibre production that maintains long‑term farm productivity and profitability while protecting soil, water, biodiversity, and resilience to climate and market risks. | F9: Area of land use | G9: =COUNTIFS(NBSAP_Commitments!$G$5:$G$1000,C9,NBSAP_Commitments!$B$5:$B$1000,Inputs!$B$6) | H9: =SUMIFS(NBSAP_Commitments!$J$5:$J$1000,NBSAP_Commitments!$G$5:$G$1000,C9,NBSAP_Commitments!$B$5:$B$1000,Inputs!$B$6)/1000000000 | I9: =IF(H9<=0,0,PERCENTRANK($H$5:$H$19,H9)) | J9: =IF(G9>=Rubric!$B$22,5,IF(G9>=Rubric!$B$23,4,IF(G9>=Rubric!$B$24,3,IF(G9>=Rubric!$B$25,2,1)))) | K9: =IF(H9<=0,1,IF(I9>=Rubric!$B$29,5,IF(I9>=Rubric!$B$30,4,IF(I9>=Rubric!$B$31,3,IF(I9>=Rubric!$B$32,2,1))))) | L9: =IFERROR(INDEX(NBSAP_Targets!$C:$C,MATCH(1,INDEX((NBSAP_Targets!$A$5:$A$500=Inputs!$B$6)*(NBSAP_Targets!$B$5:$B$500=C9),0),0)+4),"[to confirm]")
A10: AFF | B10: Agriculture, forestry and fisheries | C10: AFF03 | D10: Sustainable fisheries and aquaculture | E10: Sustainable fisheries are fisheries managed so fish stocks remain healthy and economically viable over the long term, avoiding overfishing and minimising ecosystem damage. | F10: Other biotic resource extraction (e.g. fish) | G10: =COUNTIFS(NBSAP_Commitments!$G$5:$G$1000,C10,NBSAP_Commitments!$B$5:$B$1000,Inputs!$B$6) | H10: =SUMIFS(NBSAP_Commitments!$J$5:$J$1000,NBSAP_Commitments!$G$5:$G$1000,C10,NBSAP_Commitments!$B$5:$B$1000,Inputs!$B$6)/1000000000 | I10: =IF(H10<=0,0,PERCENTRANK($H$5:$H$19,H10)) | J10: =IF(G10>=Rubric!$B$22,5,IF(G10>=Rubric!$B$23,4,IF(G10>=Rubric!$B$24,3,IF(G10>=Rubric!$B$25,2,1)))) | K10: =IF(H10<=0,1,IF(I10>=Rubric!$B$29,5,IF(I10>=Rubric!$B$30,4,IF(I10>=Rubric!$B$31,3,IF(I10>=Rubric!$B$32,2,1))))) | L10: =IFERROR(INDEX(NBSAP_Targets!$C:$C,MATCH(1,INDEX((NBSAP_Targets!$A$5:$A$500=Inputs!$B$6)*(NBSAP_Targets!$B$5:$B$500=C10),0),0)+4),"[to confirm]")
A11: UD | B11: Urban development and infrastructure | C11: UD01 | D11: Nature-positive buildings | E11: Designing buildings and construction systems that reduce pressure on ecosystems and actively support biodiversity | F11: Other biotic resource extraction (e.g. timber) | G11: =COUNTIFS(NBSAP_Commitments!$G$5:$G$1000,C11,NBSAP_Commitments!$B$5:$B$1000,Inputs!$B$6) | H11: =SUMIFS(NBSAP_Commitments!$J$5:$J$1000,NBSAP_Commitments!$G$5:$G$1000,C11,NBSAP_Commitments!$B$5:$B$1000,Inputs!$B$6)/1000000000 | I11: =IF(H11<=0,0,PERCENTRANK($H$5:$H$19,H11)) | J11: =IF(G11>=Rubric!$B$22,5,IF(G11>=Rubric!$B$23,4,IF(G11>=Rubric!$B$24,3,IF(G11>=Rubric!$B$25,2,1)))) | K11: =IF(H11<=0,1,IF(I11>=Rubric!$B$29,5,IF(I11>=Rubric!$B$30,4,IF(I11>=Rubric!$B$31,3,IF(I11>=Rubric!$B$32,2,1))))) | L11: =IFERROR(INDEX(NBSAP_Targets!$C:$C,MATCH(1,INDEX((NBSAP_Targets!$A$5:$A$500=Inputs!$B$6)*(NBSAP_Targets!$B$5:$B$500=C11),0),0)+4),"[to confirm]")
A12: UD | B12: Urban development and infrastructure | C12: UD02 | D12: Green-blue infrastructure, corridors and regeneration | E12: Economic activities that design, restore, and manage interconnected green and water‑based systems to enhance biodiversity, ecosystem connectivity, climate resilience, and nature‑positive urban and infrastructure regeneration. | F12: Area of land use | G12: =COUNTIFS(NBSAP_Commitments!$G$5:$G$1000,C12,NBSAP_Commitments!$B$5:$B$1000,Inputs!$B$6) | H12: =SUMIFS(NBSAP_Commitments!$J$5:$J$1000,NBSAP_Commitments!$G$5:$G$1000,C12,NBSAP_Commitments!$B$5:$B$1000,Inputs!$B$6)/1000000000 | I12: =IF(H12<=0,0,PERCENTRANK($H$5:$H$19,H12)) | J12: =IF(G12>=Rubric!$B$22,5,IF(G12>=Rubric!$B$23,4,IF(G12>=Rubric!$B$24,3,IF(G12>=Rubric!$B$25,2,1)))) | K12: =IF(H12<=0,1,IF(I12>=Rubric!$B$29,5,IF(I12>=Rubric!$B$30,4,IF(I12>=Rubric!$B$31,3,IF(I12>=Rubric!$B$32,2,1))))) | L12: =IFERROR(INDEX(NBSAP_Targets!$C:$C,MATCH(1,INDEX((NBSAP_Targets!$A$5:$A$500=Inputs!$B$6)*(NBSAP_Targets!$B$5:$B$500=C12),0),0)+4),"[to confirm]")
A13: UD | B13: Urban development and infrastructure | C13: UD03 | D13: Land-use change and habitat protection | E13: Economic activities and interventions that prevent, reduce, or reverse the conversion and degradation of natural ecosystems by protecting habitats and influencing how land is allocated, managed, and conserved. | F13: Area of land use | G13: =COUNTIFS(NBSAP_Commitments!$G$5:$G$1000,C13,NBSAP_Commitments!$B$5:$B$1000,Inputs!$B$6) | H13: =SUMIFS(NBSAP_Commitments!$J$5:$J$1000,NBSAP_Commitments!$G$5:$G$1000,C13,NBSAP_Commitments!$B$5:$B$1000,Inputs!$B$6)/1000000000 | I13: =IF(H13<=0,0,PERCENTRANK($H$5:$H$19,H13)) | J13: =IF(G13>=Rubric!$B$22,5,IF(G13>=Rubric!$B$23,4,IF(G13>=Rubric!$B$24,3,IF(G13>=Rubric!$B$25,2,1)))) | K13: =IF(H13<=0,1,IF(I13>=Rubric!$B$29,5,IF(I13>=Rubric!$B$30,4,IF(I13>=Rubric!$B$31,3,IF(I13>=Rubric!$B$32,2,1))))) | L13: =IFERROR(INDEX(NBSAP_Targets!$C:$C,MATCH(1,INDEX((NBSAP_Targets!$A$5:$A$500=Inputs!$B$6)*(NBSAP_Targets!$B$5:$B$500=C13),0),0)+4),"[to confirm]")
A14: DM | B14: Disaster management and adaptation | C14: DM01 | D14: Risk reduction and prevention | E14: Actions that protect, restore, or sustainably manage biodiversity and ecosystems to reduce the likelihood and intensity of hazards by addressing ecological degradation before risks materialise. | F14: Disturbance | G14: =COUNTIFS(NBSAP_Commitments!$G$5:$G$1000,C14,NBSAP_Commitments!$B$5:$B$1000,Inputs!$B$6) | H14: =SUMIFS(NBSAP_Commitments!$J$5:$J$1000,NBSAP_Commitments!$G$5:$G$1000,C14,NBSAP_Commitments!$B$5:$B$1000,Inputs!$B$6)/1000000000 | I14: =IF(H14<=0,0,PERCENTRANK($H$5:$H$19,H14)) | J14: =IF(G14>=Rubric!$B$22,5,IF(G14>=Rubric!$B$23,4,IF(G14>=Rubric!$B$24,3,IF(G14>=Rubric!$B$25,2,1)))) | K14: =IF(H14<=0,1,IF(I14>=Rubric!$B$29,5,IF(I14>=Rubric!$B$30,4,IF(I14>=Rubric!$B$31,3,IF(I14>=Rubric!$B$32,2,1))))) | L14: =IFERROR(INDEX(NBSAP_Targets!$C:$C,MATCH(1,INDEX((NBSAP_Targets!$A$5:$A$500=Inputs!$B$6)*(NBSAP_Targets!$B$5:$B$500=C14),0),0)+4),"[to confirm]")
A15: DM | B15: Disaster management and adaptation | C15: DM02 | D15: Flood mitigation | E15: Flood mitigation refers to reducing the likelihood and impacts of flooding by working with natural systems—such as wetlands, floodplains, soils, and vegetation—to slow, store, and safely absorb excess water while enhancing ecosystem health. | F15: Disturbance | G15: =COUNTIFS(NBSAP_Commitments!$G$5:$G$1000,C15,NBSAP_Commitments!$B$5:$B$1000,Inputs!$B$6) | H15: =SUMIFS(NBSAP_Commitments!$J$5:$J$1000,NBSAP_Commitments!$G$5:$G$1000,C15,NBSAP_Commitments!$B$5:$B$1000,Inputs!$B$6)/1000000000 | I15: =IF(H15<=0,0,PERCENTRANK($H$5:$H$19,H15)) | J15: =IF(G15>=Rubric!$B$22,5,IF(G15>=Rubric!$B$23,4,IF(G15>=Rubric!$B$24,3,IF(G15>=Rubric!$B$25,2,1)))) | K15: =IF(H15<=0,1,IF(I15>=Rubric!$B$29,5,IF(I15>=Rubric!$B$30,4,IF(I15>=Rubric!$B$31,3,IF(I15>=Rubric!$B$32,2,1))))) | L15: =IFERROR(INDEX(NBSAP_Targets!$C:$C,MATCH(1,INDEX((NBSAP_Targets!$A$5:$A$500=Inputs!$B$6)*(NBSAP_Targets!$B$5:$B$500=C15),0),0)+4),"[to confirm]")
A16: DM | B16: Disaster management and adaptation | C16: DM03 | D16: Long-term adaptation and resilience | E16: Strategies that enhance the capacity of biodiversity and ecosystems to adapt to long‑term and compounding pressures, enabling them to withstand, recover from, and continue functioning under future environmental change. | F16: Disturbance | G16: =COUNTIFS(NBSAP_Commitments!$G$5:$G$1000,C16,NBSAP_Commitments!$B$5:$B$1000,Inputs!$B$6) | H16: =SUMIFS(NBSAP_Commitments!$J$5:$J$1000,NBSAP_Commitments!$G$5:$G$1000,C16,NBSAP_Commitments!$B$5:$B$1000,Inputs!$B$6)/1000000000 | I16: =IF(H16<=0,0,PERCENTRANK($H$5:$H$19,H16)) | J16: =IF(G16>=Rubric!$B$22,5,IF(G16>=Rubric!$B$23,4,IF(G16>=Rubric!$B$24,3,IF(G16>=Rubric!$B$25,2,1)))) | K16: =IF(H16<=0,1,IF(I16>=Rubric!$B$29,5,IF(I16>=Rubric!$B$30,4,IF(I16>=Rubric!$B$31,3,IF(I16>=Rubric!$B$32,2,1))))) | L16: =IFERROR(INDEX(NBSAP_Targets!$C:$C,MATCH(1,INDEX((NBSAP_Targets!$A$5:$A$500=Inputs!$B$6)*(NBSAP_Targets!$B$5:$B$500=C16),0),0)+4),"[to confirm]")
... A19: P | B19: Pollution and waste | C19: P03 | D19: Air pollution, disturbances & noise pollution | E19: Emissions and physical disturbances arising from human activities—such as airborne pollutants, artificial noise, and other disruptions—that impair air quality and interfere with ecosystem functioning, species behaviour, and biodiversity health. | F19: Emissions of non-GHG air pollutants | G19: =COUNTIFS(NBSAP_Commitments!$G$5:$G$1000,C19,NBSAP_Commitments!$B$5:$B$1000,Inputs!$B$6) | H19: =SUMIFS(NBSAP_Commitments!$J$5:$J$1000,NBSAP_Commitments!$G$5:$G$1000,C19,NBSAP_Commitments!$B$5:$B$1000,Inputs!$B$6)/1000000000 | I19: =IF(H19<=0,0,PERCENTRANK($H$5:$H$19,H19)) | J19: =IF(G19>=Rubric!$B$22,5,IF(G19>=Rubric!$B$23,4,IF(G19>=Rubric!$B$24,3,IF(G19>=Rubric!$B$25,2,1)))) | K19: =IF(H19<=0,1,IF(I19>=Rubric!$B$29,5,IF(I19>=Rubric!$B$30,4,IF(I19>=Rubric!$B$31,3,IF(I19>=Rubric!$B$32,2,1))))) | L19: =IFERROR(INDEX(NBSAP_Targets!$C:$C,MATCH(1,INDEX((NBSAP_Targets!$A$5:$A$500=Inputs!$B$6)*(NBSAP_Targets!$B$5:$B$500=C19),0),0)+4),"[to confirm]")

Sheet NBSAP_Commitments
A1: NBSAP commitments – all countries (from EY workbook, Market_Examples)
A2: Paste refreshed rows from the EY workbook as values. Column G is a formula: always use the sub-market parent.
A4: Example_ID | B4: Country_ID | C4: Market_ID (as tagged) | D4: Sub_Market_ID | E4: Commitment | F4: Value (local) | G4: SubTheme_ID (taxonomy parent) | H4: Currency | I4: Tag consistent? | J4: Value (USD) | K4: Financing method | L4: Financial product | M4: Source
A5: M01 | B5: GBR | C5: DM01 | D5: A03 | E5: Investment into storm overflows to deliver 50% reduction in spills | F5: 10000000000 | G5: =IFERROR(INDEX(Sub_Markets!$B$5:$B$77,MATCH(D5,Sub_Markets!$A$5:$A$77,0)),C5) | H5: GBP | I5: =IF(C5=G5,"Yes","No") | J5: 13200000000 | K5: Equity and debt finance | L5: Term debt and equity | M5: NBSAP
A6: M02 | B6: GBR | C6: W01 | D6: WU01 | E6: Water Management Grant to fund more on-farm reservoirs and better irrigation equipment | F6: 10000000 | G6: =IFERROR(INDEX(Sub_Markets!$B$5:$B$77,MATCH(D6,Sub_Markets!$A$5:$A$77,0)),C6) | H6: GBP | I6: =IF(C6=G6,"Yes","No") | J6: 13200000 | K6: Grant financing | L6: Restricted funds | M6: More funding for farmers as new blueprint for water announced - GOV.UK
A7: M03 | B7: GBR | C7: W01 | D7: WU02 | E7: Water efficient fund to support new water efficiency approaches between 2025 and 2030 | F7: 100000000 | G7: =IFERROR(INDEX(Sub_Markets!$B$5:$B$77,MATCH(D7,Sub_Markets!$A$5:$A$77,0)),C7) | H7: GBP | I7: =IF(C7=G7,"Yes","No") | J7: 132000000 | K7: Grant financing | L7: Accelerators | M7: MOSL responds to Ofwat's second consultation on its £100m water efficiency fund - MOSL
A8: M04 | B8: GBR | C8: W02 | D8: WU09 | E8: Funding for comprehensive cross border research to understand pollution and other pressures | F8: 1000000 | G8: =IFERROR(INDEX(Sub_Markets!$B$5:$B$77,MATCH(D8,Sub_Markets!$A$5:$A$77,0)),C8) | H8: GBP | I8: =IF(C8=G8,"Yes","No") | J8: 1320000 | K8: Grant financing | L8: Accelerators | M8: NBSAP
A9: M05 | B9: GBR | C9: W02 | D9: WU14 | E9: Investment into restoration of chalk stream | F9: 2000000000 | G9: =IFERROR(INDEX(Sub_Markets!$B$5:$B$77,MATCH(D9,Sub_Markets!$A$5:$A$77,0)),C9) | H9: GBP | I9: =IF(C9=G9,"Yes","No") | J9: 2640000000 | K9: Equity and debt finance | L9: Term debt and equity | M9: NBSAP
A10: M06 | B10: GBR | C10: W03 | D10: WU15 | E10: Funding based on water fines and penalties into water environment | F10: 100000000 | G10: =IFERROR(INDEX(Sub_Markets!$B$5:$B$77,MATCH(D10,Sub_Markets!$A$5:$A$77,0)),C10) | H10: GBP | I10: =IF(C10=G10,"Yes","No") | J10: 132000000 | K10: Grant financing | L10: Restricted funds | M10: NBSAP
A11: M07 | B11: GBR | C11: W01 | D11: WU01 | E11: Funding under Catchment Sensitive Farming programme to advise farmers on reducing pollution | F11: 30000000 | G11: =IFERROR(INDEX(Sub_Markets!$B$5:$B$77,MATCH(D11,Sub_Markets!$A$5:$A$77,0)),C11) | H11: GBP | I11: =IF(C11=G11,"Yes","No") | J11: 39600000 | K11: Grant financing | L11: Restricted funds | M11: Catchment Sensitive Farming funding almost doubled to help farmers tackle water pollution - CIWEM
A12: M08 | B12: GBR | C12: W02 | D12: WU11 | E12: Investment into vital infrastructure to improve the water quality of rivers, lakes and coastal waters and secure future water supplies | F12: 1600000000 | G12: =IFERROR(INDEX(Sub_Markets!$B$5:$B$77,MATCH(D12,Sub_Markets!$A$5:$A$77,0)),C12) | H12: GBP | I12: =IF(C12=G12,"Yes","No") | J12: 2112000000 | K12: Equity and debt finance | L12: Term debt and equity | M12: Plan for Water: our integrated plan for delivering clean and plentiful water - GOV.UK
A13: M09 | B13: GBR | C13: DM01 | D13: A03 | E13: Reduce storm overflow discharges | F13: 2240000000 | G13: =IFERROR(INDEX(Sub_Markets!$B$5:$B$77,MATCH(D13,Sub_Markets!$A$5:$A$77,0)),C13) | H13: GBP | I13: =IF(C13=G13,"Yes","No") | J13: 2956800000 | K13: Equity and debt finance | L13: Term debt and equity | M13: Plan for Water: our integrated plan for delivering clean and plentiful water - GOV.UK
A14: M10 | B14: GBR | C14: W01 | D14: WU01 | E14: Slurry Infrastructure Grant to reduce run-off | F14: 34000000 | G14: =IFERROR(INDEX(Sub_Markets!$B$5:$B$77,MATCH(D14,Sub_Markets!$A$5:$A$77,0)),C14) | H14: GBP | I14: =IF(C14=G14,"Yes","No") | J14: 44880000 | K14: Grant financing | L14: Restricted funds | M14: More funding for farmers as new blueprint for water announced - GOV.UK
A15: M100 | B15: PRT | C15: AFF03 | D15: FO14 | E15: National funding from EMFAF Programme to support sustainable to support sustainable fisheries | F15: 200842800 | G15: =IFERROR(INDEX(Sub_Markets!$B$5:$B$77,MATCH(D15,Sub_Markets!$A$5:$A$77,0)),C15) | H15: EUR | I15: =IF(C15=G15,"Yes","No") | J15: 230969220 | K15: Grant financing | L15: Restricted funds | M15: Irish EMFAF programme 2021-27 - EU Funds
A16: M101 | B16: PRT | C16: AFF03 | D16: FO15 | E16: National funding from EMFAF Programme to support sustainable to support sustainable aquaculture | F16: 193284200 | G16: =IFERROR(INDEX(Sub_Markets!$B$5:$B$77,MATCH(D16,Sub_Markets!$A$5:$A$77,0)),C16) | H16: EUR | I16: =IF(C16=G16,"Yes","No") | J16: 222276830 | K16: Grant financing | L16: Restricted funds | M16: Irish EMFAF programme 2021-27 - EU Funds
... A193: M99 | B193: PRT | C193: AFF02 | D193: FO07 | E193: Portion of CAP for supporting biodiversity-friendly farming practises | F193: 2500000000 | G193: =IFERROR(INDEX(Sub_Markets!$B$5:$B$77,MATCH(D193,Sub_Markets!$A$5:$A$77,0)),C193) | H193: EUR | I193: =IF(C193=G193,"Yes","No") | J193: 2875000000 | K193: Grant financing | L193: Restricted funds | M193: CAP Funding programme

Sheet NBSAP_Targets
A1: NBSAP goals/targets by country and sub-theme
A2: Complete for the country being run (Copilot Step 4). Pre-filled from the EY workbook where available.
A4: Country_ID | B4: SubTheme_ID | C4: NBSAP goal / target reference | D4: Policy signal strength | E4: Page
A5: GBR | B5: W01 | C5: Goal 3: Water | D5: High | E5: Page 47

Sheet Evidence_Log
A1: Evidence log
A2: Evidence type: Commitment | Quantified target | Policy | Exposure | Financing or product | Partnership | Performance metric | Disclosure | Governance. Scope: Own operations | Value chain / portfolio | Products and services | External driver.
A4: Evidence_ID | B4: Source_ID | C4: Page / tab | D4: Verbatim quote or figure (≤25 words) | E4: Evidence type | F4: Scope | G4: Summary
A5: EV-001 | B5: SRC-01 | C5: p.4 | D5: To date, it has spanned 238,494 hectares of farmland across 685 farms | E5: Performance metric | F5: Value chain / portfolio | G5: EXAMPLE – delete

Sheet NBSAP_Mapping
A1: Evidence mapped to taxonomy
A2: Evidence class: Client exposure | Client action | Client position | External driver. Use XC for cross-cutting items. Column I is a helper used for confidence.
A4: Evidence_ID | B4: Source_ID | C4: Evidence class | D4: Primary SubTheme_ID | E4: Primary Sub_Market_ID | F4: Secondary SubTheme_ID | G4: Mapping strength | H4: Rationale | I4: First client item for this source and sub-theme (helper)
A5: EV-001 | B5: =IF(A5="","",IFERROR(INDEX(Evidence_Log!$B:$B,MATCH(A5,Evidence_Log!$A:$A,0)),"check ID")) | C5: Client action | D5: AFF02 | E5: FO08 | F5: W02 | G5: Direct | H5: EXAMPLE – delete | I5: =IF(OR(A5="",C5="External driver"),0,IF(COUNTIFS(D$5:D5,D5,B$5:B5,B5,C$5:C5,"<>External driver")=1,1,0))
B6: =IF(A6="","",IFERROR(INDEX(Evidence_Log!$B:$B,MATCH(A6,Evidence_Log!$A:$A,0)),"check ID")) | I6: =IF(OR(A6="",C6="External driver"),0,IF(COUNTIFS(D$5:D6,D6,B$5:B6,B6,C$5:C6,"<>External driver")=1,1,0))
B7: =IF(A7="","",IFERROR(INDEX(Evidence_Log!$B:$B,MATCH(A7,Evidence_Log!$A:$A,0)),"check ID")) | I7: =IF(OR(A7="",C7="External driver"),0,IF(COUNTIFS(D$5:D7,D7,B$5:B7,B7,C$5:C7,"<>External driver")=1,1,0))
B8: =IF(A8="","",IFERROR(INDEX(Evidence_Log!$B:$B,MATCH(A8,Evidence_Log!$A:$A,0)),"check ID")) | I8: =IF(OR(A8="",C8="External driver"),0,IF(COUNTIFS(D$5:D8,D8,B$5:B8,B8,C$5:C8,"<>External driver")=1,1,0))
B9: =IF(A9="","",IFERROR(INDEX(Evidence_Log!$B:$B,MATCH(A9,Evidence_Log!$A:$A,0)),"check ID")) | I9: =IF(OR(A9="",C9="External driver"),0,IF(COUNTIFS(D$5:D9,D9,B$5:B9,B9,C$5:C9,"<>External driver")=1,1,0))
B10: =IF(A10="","",IFERROR(INDEX(Evidence_Log!$B:$B,MATCH(A10,Evidence_Log!$A:$A,0)),"check ID")) | I10: =IF(OR(A10="",C10="External driver"),0,IF(COUNTIFS(D$5:D10,D10,B$5:B10,B10,C$5:C10,"<>External driver")=1,1,0))
B11: =IF(A11="","",IFERROR(INDEX(Evidence_Log!$B:$B,MATCH(A11,Evidence_Log!$A:$A,0)),"check ID")) | I11: =IF(OR(A11="",C11="External driver"),0,IF(COUNTIFS(D$5:D11,D11,B$5:B11,B11,C$5:C11,"<>External driver")=1,1,0))
B12: =IF(A12="","",IFERROR(INDEX(Evidence_Log!$B:$B,MATCH(A12,Evidence_Log!$A:$A,0)),"check ID")) | I12: =IF(OR(A12="",C12="External driver"),0,IF(COUNTIFS(D$5:D12,D12,B$5:B12,B12,C$5:C12,"<>External driver")=1,1,0))
B13: =IF(A13="","",IFERROR(INDEX(Evidence_Log!$B:$B,MATCH(A13,Evidence_Log!$A:$A,0)),"check ID")) | I13: =IF(OR(A13="",C13="External driver"),0,IF(COUNTIFS(D$5:D13,D13,B$5:B13,B13,C$5:C13,"<>External driver")=1,1,0))
B14: =IF(A14="","",IFERROR(INDEX(Evidence_Log!$B:$B,MATCH(A14,Evidence_Log!$A:$A,0)),"check ID")) | I14: =IF(OR(A14="",C14="External driver"),0,IF(COUNTIFS(D$5:D14,D14,B$5:B14,B14,C$5:C14,"<>External driver")=1,1,0))
B15: =IF(A15="","",IFERROR(INDEX(Evidence_Log!$B:$B,MATCH(A15,Evidence_Log!$A:$A,0)),"check ID")) | I15: =IF(OR(A15="",C15="External driver"),0,IF(COUNTIFS(D$5:D15,D15,B$5:B15,B15,C$5:C15,"<>External driver")=1,1,0))
B16: =IF(A16="","",IFERROR(INDEX(Evidence_Log!$B:$B,MATCH(A16,Evidence_Log!$A:$A,0)),"check ID")) | I16: =IF(OR(A16="",C16="External driver"),0,IF(COUNTIFS(D$5:D16,D16,B$5:B16,B16,C$5:C16,"<>External driver")=1,1,0))
B17: =IF(A17="","",IFERROR(INDEX(Evidence_Log!$B:$B,MATCH(A17,Evidence_Log!$A:$A,0)),"check ID")) | I17: =IF(OR(A17="",C17="External driver"),0,IF(COUNTIFS(D$5:D17,D17,B$5:B17,B17,C$5:C17,"<>External driver")=1,1,0))
... B304: =IF(A304="","",IFERROR(INDEX(Evidence_Log!$B:$B,MATCH(A304,Evidence_Log!$A:$A,0)),"check ID")) | I304: =IF(OR(A304="",C304="External driver"),0,IF(COUNTIFS(D$5:D304,D304,B$5:B304,B304,C$5:C304,"<>External driver")=1,1,0))

Sheet Rubric
A1: Scoring rubric
A4: Code | B4: Criterion | C4: Weight | D4: What 5 / 1 means
A5: C1 | B5: Materiality to client | C5: 0.3 | D5: 5 = core business line, disclosed material topic or large exposure; 1 = no identifiable relevance in sources
A6: C2 | B6: Action gap | C6: 0.25 | D6: 5 = material but no disclosed action; 3 = commitments/eligibility criteria without targets; 1 = quantified nature targets with reported progress. Cap at 2 when C1 ≤ 2.
A7: C3 | B7: NBSAP emphasis | C7: 0.2 | D7: Number of NBSAP commitments for the sub-theme in the selected country (bands below)
A8: C4 | B8: Regulatory and market momentum | C8: 0.15 | D8: 5 = mandatory requirements in force/confirmed; 1 = none identified in sources
A9: C5 | B9: Market opportunity | C9: 0.1 | D9: Relative rank of NBSAP commitment value within the selected country (bands below); 1 if no commitments
B10: Total weight | C10: =SUM(C5:C9)
A12: Tiers
B13: High: score at least | C13: 4
B14: Medium: score at least | C14: 3
D16: Tie-break: higher C1, then higher C2, then more client evidence items.
A18: Confidence
D19: High: 3+ client items from 2+ sources with at least one Direct mapping. Medium: 1+ client items. Low: no client evidence.
A21: C3 bands | B21: Commitments (no.) at least | C21: Score
B22: 4 | C22: 5
B23: 3 | C23: 4
B24: 2 | C24: 3
B25: 1 | C25: 2
B26: 0 | C26: 1
A28: C5 bands | B28: Relative rank at least | C28: Score
B29: 0.8 | C29: 5
B30: 0.6 | C30: 4
B31: 0.4 | C31: 3
B32: 0.2 | C32: 2

Sheet Scoring
A1: Scoring and ranking
A2: Paste Copilot Step 5 output into the blue columns (E, F, H, P, Q, R, T, U). Everything else calculates. Sort by Rank for the slide.
A4: Rank | B4: SubTheme_ID | C4: Theme | D4: Sub-theme | E4: C1 Materiality | F4: C2 Action gap | G4: C3 NBSAP emphasis | H4: C4 Regulatory & market momentum | I4: C5 Market opportunity | J4: Weighted score | K4: Tier | L4: Confidence | M4: Client evidence (no.) | N4: Client sources (no.) | O4: Direct mappings (no.) | P4: Evidence_IDs | Q4: Rationale | R4: Client exposure (as disclosed) | S4: Sort key | T4: Key evidence for slide (≤12 words) | U4: Exposure for slide (≤4 words)
A5: =RANK(S5,$S$5:$S$19) | B5: W01 | C5: =Taxonomy!B5 | D5: =Taxonomy!D5 | G5: =Taxonomy!J5 | I5: =Taxonomy!K5 | J5: =IF(COUNT(E5,F5,H5)<3,"",ROUND(E5*Rubric!$C$5+F5*Rubric!$C$6+G5*Rubric!$C$7+H5*Rubric!$C$8+I5*Rubric!$C$9+0.000000001,1)) | K5: =IF(J5="","",IF(J5>=Rubric!$C$13,"High",IF(J5>=Rubric!$C$14,"Medium","Low"))) | L5: =IF(M5=0,"Low",IF(AND(M5>=3,N5>=2,O5>=1),"High","Medium")) | M5: =COUNTIFS(NBSAP_Mapping!$D$5:$D$304,B5,NBSAP_Mapping!$C$5:$C$304,"<>External driver",NBSAP_Mapping!$C$5:$C$304,"<>") | N5: =SUMIFS(NBSAP_Mapping!$I$5:$I$304,NBSAP_Mapping!$D$5:$D$304,B5) | O5: =COUNTIFS(NBSAP_Mapping!$D$5:$D$304,B5,NBSAP_Mapping!$C$5:$C$304,"<>External driver",NBSAP_Mapping!$C$5:$C$304,"<>",NBSAP_Mapping!$G$5:$G$304,"Direct") | S5: =IF(J5="",0,J5*10000+E5*100+F5*10+MIN(M5,9))-ROW()/100000
A6: =RANK(S6,$S$5:$S$19) | B6: W02 | C6: =Taxonomy!B6 | D6: =Taxonomy!D6 | G6: =Taxonomy!J6 | I6: =Taxonomy!K6 | J6: =IF(COUNT(E6,F6,H6)<3,"",ROUND(E6*Rubric!$C$5+F6*Rubric!$C$6+G6*Rubric!$C$7+H6*Rubric!$C$8+I6*Rubric!$C$9+0.000000001,1)) | K6: =IF(J6="","",IF(J6>=Rubric!$C$13,"High",IF(J6>=Rubric!$C$14,"Medium","Low"))) | L6: =IF(M6=0,"Low",IF(AND(M6>=3,N6>=2,O6>=1),"High","Medium")) | M6: =COUNTIFS(NBSAP_Mapping!$D$5:$D$304,B6,NBSAP_Mapping!$C$5:$C$304,"<>External driver",NBSAP_Mapping!$C$5:$C$304,"<>") | N6: =SUMIFS(NBSAP_Mapping!$I$5:$I$304,NBSAP_Mapping!$D$5:$D$304,B6) | O6: =COUNTIFS(NBSAP_Mapping!$D$5:$D$304,B6,NBSAP_Mapping!$C$5:$C$304,"<>External driver",NBSAP_Mapping!$C$5:$C$304,"<>",NBSAP_Mapping!$G$5:$G$304,"Direct") | S6: =IF(J6="",0,J6*10000+E6*100+F6*10+MIN(M6,9))-ROW()/100000
A7: =RANK(S7,$S$5:$S$19) | B7: W03 | C7: =Taxonomy!B7 | D7: =Taxonomy!D7 | G7: =Taxonomy!J7 | I7: =Taxonomy!K7 | J7: =IF(COUNT(E7,F7,H7)<3,"",ROUND(E7*Rubric!$C$5+F7*Rubric!$C$6+G7*Rubric!$C$7+H7*Rubric!$C$8+I7*Rubric!$C$9+0.000000001,1)) | K7: =IF(J7="","",IF(J7>=Rubric!$C$13,"High",IF(J7>=Rubric!$C$14,"Medium","Low"))) | L7: =IF(M7=0,"Low",IF(AND(M7>=3,N7>=2,O7>=1),"High","Medium")) | M7: =COUNTIFS(NBSAP_Mapping!$D$5:$D$304,B7,NBSAP_Mapping!$C$5:$C$304,"<>External driver",NBSAP_Mapping!$C$5:$C$304,"<>") | N7: =SUMIFS(NBSAP_Mapping!$I$5:$I$304,NBSAP_Mapping!$D$5:$D$304,B7) | O7: =COUNTIFS(NBSAP_Mapping!$D$5:$D$304,B7,NBSAP_Mapping!$C$5:$C$304,"<>External driver",NBSAP_Mapping!$C$5:$C$304,"<>",NBSAP_Mapping!$G$5:$G$304,"Direct") | S7: =IF(J7="",0,J7*10000+E7*100+F7*10+MIN(M7,9))-ROW()/100000
A8: =RANK(S8,$S$5:$S$19) | B8: AFF01 | C8: =Taxonomy!B8 | D8: =Taxonomy!D8 | G8: =Taxonomy!J8 | I8: =Taxonomy!K8 | J8: =IF(COUNT(E8,F8,H8)<3,"",ROUND(E8*Rubric!$C$5+F8*Rubric!$C$6+G8*Rubric!$C$7+H8*Rubric!$C$8+I8*Rubric!$C$9+0.000000001,1)) | K8: =IF(J8="","",IF(J8>=Rubric!$C$13,"High",IF(J8>=Rubric!$C$14,"Medium","Low"))) | L8: =IF(M8=0,"Low",IF(AND(M8>=3,N8>=2,O8>=1),"High","Medium")) | M8: =COUNTIFS(NBSAP_Mapping!$D$5:$D$304,B8,NBSAP_Mapping!$C$5:$C$304,"<>External driver",NBSAP_Mapping!$C$5:$C$304,"<>") | N8: =SUMIFS(NBSAP_Mapping!$I$5:$I$304,NBSAP_Mapping!$D$5:$D$304,B8) | O8: =COUNTIFS(NBSAP_Mapping!$D$5:$D$304,B8,NBSAP_Mapping!$C$5:$C$304,"<>External driver",NBSAP_Mapping!$C$5:$C$304,"<>",NBSAP_Mapping!$G$5:$G$304,"Direct") | S8: =IF(J8="",0,J8*10000+E8*100+F8*10+MIN(M8,9))-ROW()/100000
A9: =RANK(S9,$S$5:$S$19) | B9: AFF02 | C9: =Taxonomy!B9 | D9: =Taxonomy!D9 | G9: =Taxonomy!J9 | I9: =Taxonomy!K9 | J9: =IF(COUNT(E9,F9,H9)<3,"",ROUND(E9*Rubric!$C$5+F9*Rubric!$C$6+G9*Rubric!$C$7+H9*Rubric!$C$8+I9*Rubric!$C$9+0.000000001,1)) | K9: =IF(J9="","",IF(J9>=Rubric!$C$13,"High",IF(J9>=Rubric!$C$14,"Medium","Low"))) | L9: =IF(M9=0,"Low",IF(AND(M9>=3,N9>=2,O9>=1),"High","Medium")) | M9: =COUNTIFS(NBSAP_Mapping!$D$5:$D$304,B9,NBSAP_Mapping!$C$5:$C$304,"<>External driver",NBSAP_Mapping!$C$5:$C$304,"<>") | N9: =SUMIFS(NBSAP_Mapping!$I$5:$I$304,NBSAP_Mapping!$D$5:$D$304,B9) | O9: =COUNTIFS(NBSAP_Mapping!$D$5:$D$304,B9,NBSAP_Mapping!$C$5:$C$304,"<>External driver",NBSAP_Mapping!$C$5:$C$304,"<>",NBSAP_Mapping!$G$5:$G$304,"Direct") | S9: =IF(J9="",0,J9*10000+E9*100+F9*10+MIN(M9,9))-ROW()/100000
A10: =RANK(S10,$S$5:$S$19) | B10: AFF03 | C10: =Taxonomy!B10 | D10: =Taxonomy!D10 | G10: =Taxonomy!J10 | I10: =Taxonomy!K10 | J10: =IF(COUNT(E10,F10,H10)<3,"",ROUND(E10*Rubric!$C$5+F10*Rubric!$C$6+G10*Rubric!$C$7+H10*Rubric!$C$8+I10*Rubric!$C$9+0.000000001,1)) | K10: =IF(J10="","",IF(J10>=Rubric!$C$13,"High",IF(J10>=Rubric!$C$14,"Medium","Low"))) | L10: =IF(M10=0,"Low",IF(AND(M10>=3,N10>=2,O10>=1),"High","Medium")) | M10: =COUNTIFS(NBSAP_Mapping!$D$5:$D$304,B10,NBSAP_Mapping!$C$5:$C$304,"<>External driver",NBSAP_Mapping!$C$5:$C$304,"<>") | N10: =SUMIFS(NBSAP_Mapping!$I$5:$I$304,NBSAP_Mapping!$D$5:$D$304,B10) | O10: =COUNTIFS(NBSAP_Mapping!$D$5:$D$304,B10,NBSAP_Mapping!$C$5:$C$304,"<>External driver",NBSAP_Mapping!$C$5:$C$304,"<>",NBSAP_Mapping!$G$5:$G$304,"Direct") | S10: =IF(J10="",0,J10*10000+E10*100+F10*10+MIN(M10,9))-ROW()/100000
A11: =RANK(S11,$S$5:$S$19) | B11: UD01 | C11: =Taxonomy!B11 | D11: =Taxonomy!D11 | G11: =Taxonomy!J11 | I11: =Taxonomy!K11 | J11: =IF(COUNT(E11,F11,H11)<3,"",ROUND(E11*Rubric!$C$5+F11*Rubric!$C$6+G11*Rubric!$C$7+H11*Rubric!$C$8+I11*Rubric!$C$9+0.000000001,1)) | K11: =IF(J11="","",IF(J11>=Rubric!$C$13,"High",IF(J11>=Rubric!$C$14,"Medium","Low"))) | L11: =IF(M11=0,"Low",IF(AND(M11>=3,N11>=2,O11>=1),"High","Medium")) | M11: =COUNTIFS(NBSAP_Mapping!$D$5:$D$304,B11,NBSAP_Mapping!$C$5:$C$304,"<>External driver",NBSAP_Mapping!$C$5:$C$304,"<>") | N11: =SUMIFS(NBSAP_Mapping!$I$5:$I$304,NBSAP_Mapping!$D$5:$D$304,B11) | O11: =COUNTIFS(NBSAP_Mapping!$D$5:$D$304,B11,NBSAP_Mapping!$C$5:$C$304,"<>External driver",NBSAP_Mapping!$C$5:$C$304,"<>",NBSAP_Mapping!$G$5:$G$304,"Direct") | S11: =IF(J11="",0,J11*10000+E11*100+F11*10+MIN(M11,9))-ROW()/100000
A12: =RANK(S12,$S$5:$S$19) | B12: UD02 | C12: =Taxonomy!B12 | D12: =Taxonomy!D12 | G12: =Taxonomy!J12 | I12: =Taxonomy!K12 | J12: =IF(COUNT(E12,F12,H12)<3,"",ROUND(E12*Rubric!$C$5+F12*Rubric!$C$6+G12*Rubric!$C$7+H12*Rubric!$C$8+I12*Rubric!$C$9+0.000000001,1)) | K12: =IF(J12="","",IF(J12>=Rubric!$C$13,"High",IF(J12>=Rubric!$C$14,"Medium","Low"))) | L12: =IF(M12=0,"Low",IF(AND(M12>=3,N12>=2,O12>=1),"High","Medium")) | M12: =COUNTIFS(NBSAP_Mapping!$D$5:$D$304,B12,NBSAP_Mapping!$C$5:$C$304,"<>External driver",NBSAP_Mapping!$C$5:$C$304,"<>") | N12: =SUMIFS(NBSAP_Mapping!$I$5:$I$304,NBSAP_Mapping!$D$5:$D$304,B12) | O12: =COUNTIFS(NBSAP_Mapping!$D$5:$D$304,B12,NBSAP_Mapping!$C$5:$C$304,"<>External driver",NBSAP_Mapping!$C$5:$C$304,"<>",NBSAP_Mapping!$G$5:$G$304,"Direct") | S12: =IF(J12="",0,J12*10000+E12*100+F12*10+MIN(M12,9))-ROW()/100000
A13: =RANK(S13,$S$5:$S$19) | B13: UD03 | C13: =Taxonomy!B13 | D13: =Taxonomy!D13 | G13: =Taxonomy!J13 | I13: =Taxonomy!K13 | J13: =IF(COUNT(E13,F13,H13)<3,"",ROUND(E13*Rubric!$C$5+F13*Rubric!$C$6+G13*Rubric!$C$7+H13*Rubric!$C$8+I13*Rubric!$C$9+0.000000001,1)) | K13: =IF(J13="","",IF(J13>=Rubric!$C$13,"High",IF(J13>=Rubric!$C$14,"Medium","Low"))) | L13: =IF(M13=0,"Low",IF(AND(M13>=3,N13>=2,O13>=1),"High","Medium")) | M13: =COUNTIFS(NBSAP_Mapping!$D$5:$D$304,B13,NBSAP_Mapping!$C$5:$C$304,"<>External driver",NBSAP_Mapping!$C$5:$C$304,"<>") | N13: =SUMIFS(NBSAP_Mapping!$I$5:$I$304,NBSAP_Mapping!$D$5:$D$304,B13) | O13: =COUNTIFS(NBSAP_Mapping!$D$5:$D$304,B13,NBSAP_Mapping!$C$5:$C$304,"<>External driver",NBSAP_Mapping!$C$5:$C$304,"<>",NBSAP_Mapping!$G$5:$G$304,"Direct") | S13: =IF(J13="",0,J13*10000+E13*100+F13*10+MIN(M13,9))-ROW()/100000
A14: =RANK(S14,$S$5:$S$19) | B14: DM01 | C14: =Taxonomy!B14 | D14: =Taxonomy!D14 | G14: =Taxonomy!J14 | I14: =Taxonomy!K14 | J14: =IF(COUNT(E14,F14,H14)<3,"",ROUND(E14*Rubric!$C$5+F14*Rubric!$C$6+G14*Rubric!$C$7+H14*Rubric!$C$8+I14*Rubric!$C$9+0.000000001,1)) | K14: =IF(J14="","",IF(J14>=Rubric!$C$13,"High",IF(J14>=Rubric!$C$14,"Medium","Low"))) | L14: =IF(M14=0,"Low",IF(AND(M14>=3,N14>=2,O14>=1),"High","Medium")) | M14: =COUNTIFS(NBSAP_Mapping!$D$5:$D$304,B14,NBSAP_Mapping!$C$5:$C$304,"<>External driver",NBSAP_Mapping!$C$5:$C$304,"<>") | N14: =SUMIFS(NBSAP_Mapping!$I$5:$I$304,NBSAP_Mapping!$D$5:$D$304,B14) | O14: =COUNTIFS(NBSAP_Mapping!$D$5:$D$304,B14,NBSAP_Mapping!$C$5:$C$304,"<>External driver",NBSAP_Mapping!$C$5:$C$304,"<>",NBSAP_Mapping!$G$5:$G$304,"Direct") | S14: =IF(J14="",0,J14*10000+E14*100+F14*10+MIN(M14,9))-ROW()/100000
A15: =RANK(S15,$S$5:$S$19) | B15: DM02 | C15: =Taxonomy!B15 | D15: =Taxonomy!D15 | G15: =Taxonomy!J15 | I15: =Taxonomy!K15 | J15: =IF(COUNT(E15,F15,H15)<3,"",ROUND(E15*Rubric!$C$5+F15*Rubric!$C$6+G15*Rubric!$C$7+H15*Rubric!$C$8+I15*Rubric!$C$9+0.000000001,1)) | K15: =IF(J15="","",IF(J15>=Rubric!$C$13,"High",IF(J15>=Rubric!$C$14,"Medium","Low"))) | L15: =IF(M15=0,"Low",IF(AND(M15>=3,N15>=2,O15>=1),"High","Medium")) | M15: =COUNTIFS(NBSAP_Mapping!$D$5:$D$304,B15,NBSAP_Mapping!$C$5:$C$304,"<>External driver",NBSAP_Mapping!$C$5:$C$304,"<>") | N15: =SUMIFS(NBSAP_Mapping!$I$5:$I$304,NBSAP_Mapping!$D$5:$D$304,B15) | O15: =COUNTIFS(NBSAP_Mapping!$D$5:$D$304,B15,NBSAP_Mapping!$C$5:$C$304,"<>External driver",NBSAP_Mapping!$C$5:$C$304,"<>",NBSAP_Mapping!$G$5:$G$304,"Direct") | S15: =IF(J15="",0,J15*10000+E15*100+F15*10+MIN(M15,9))-ROW()/100000
A16: =RANK(S16,$S$5:$S$19) | B16: DM03 | C16: =Taxonomy!B16 | D16: =Taxonomy!D16 | G16: =Taxonomy!J16 | I16: =Taxonomy!K16 | J16: =IF(COUNT(E16,F16,H16)<3,"",ROUND(E16*Rubric!$C$5+F16*Rubric!$C$6+G16*Rubric!$C$7+H16*Rubric!$C$8+I16*Rubric!$C$9+0.000000001,1)) | K16: =IF(J16="","",IF(J16>=Rubric!$C$13,"High",IF(J16>=Rubric!$C$14,"Medium","Low"))) | L16: =IF(M16=0,"Low",IF(AND(M16>=3,N16>=2,O16>=1),"High","Medium")) | M16: =COUNTIFS(NBSAP_Mapping!$D$5:$D$304,B16,NBSAP_Mapping!$C$5:$C$304,"<>External driver",NBSAP_Mapping!$C$5:$C$304,"<>") | N16: =SUMIFS(NBSAP_Mapping!$I$5:$I$304,NBSAP_Mapping!$D$5:$D$304,B16) | O16: =COUNTIFS(NBSAP_Mapping!$D$5:$D$304,B16,NBSAP_Mapping!$C$5:$C$304,"<>External driver",NBSAP_Mapping!$C$5:$C$304,"<>",NBSAP_Mapping!$G$5:$G$304,"Direct") | S16: =IF(J16="",0,J16*10000+E16*100+F16*10+MIN(M16,9))-ROW()/100000
... A19: =RANK(S19,$S$5:$S$19) | B19: P03 | C19: =Taxonomy!B19 | D19: =Taxonomy!D19 | G19: =Taxonomy!J19 | I19: =Taxonomy!K19 | J19: =IF(COUNT(E19,F19,H19)<3,"",ROUND(E19*Rubric!$C$5+F19*Rubric!$C$6+G19*Rubric!$C$7+H19*Rubric!$C$8+I19*Rubric!$C$9+0.000000001,1)) | K19: =IF(J19="","",IF(J19>=Rubric!$C$13,"High",IF(J19>=Rubric!$C$14,"Medium","Low"))) | L19: =IF(M19=0,"Low",IF(AND(M19>=3,N19>=2,O19>=1),"High","Medium")) | M19: =COUNTIFS(NBSAP_Mapping!$D$5:$D$304,B19,NBSAP_Mapping!$C$5:$C$304,"<>External driver",NBSAP_Mapping!$C$5:$C$304,"<>") | N19: =SUMIFS(NBSAP_Mapping!$I$5:$I$304,NBSAP_Mapping!$D$5:$D$304,B19) | O19: =COUNTIFS(NBSAP_Mapping!$D$5:$D$304,B19,NBSAP_Mapping!$C$5:$C$304,"<>External driver",NBSAP_Mapping!$C$5:$C$304,"<>",NBSAP_Mapping!$G$5:$G$304,"Direct") | S19: =IF(J19="",0,J19*10000+E19*100+F19*10+MIN(M19,9))-ROW()/100000

Sheet Slide_Content
A1: Slide content (read by build_deck.py)
A2: Paste Copilot Step 7 output here (Key | Value). build_deck.py reads this tab plus the Scoring tab to build the EY deck.
A4: Key | B4: Value | C4: Guidance
A5: cover_title | C5: Deck title, 8–12 words
A6: cover_date | C6: e.g. 7th October 2026
A7: client_name | C7: Short client name used on every slide line
A8: s1_title | C8: Action title ≤75 characters
A9: s1_section | C9: Executive summary
A10: s1_stat1_value | C10: e.g. £60.0bn
A11: s1_stat1_label | C11: ≤12 words
A12: s1_stat2_value | C12: e.g. 4 of 15
A13: s1_stat2_label | C13: ≤12 words
A14: s1_stat3_value | C14: e.g. £70.9bn
A15: s1_stat3_label | C15: ≤12 words
A16: s1_context | C16: 1 sentence
... A56: s3_notes | C56: Sources, one per line

Sheet QA_Log
A1: Quality checks
A4: # | B4: Check | C4: Result
A5: 1 | B5: Country_ID recognised | C5: =IF(ISNUMBER(MATCH(Inputs!B6,Countries!A:A,0)),"Pass","Fail")
A6: 2 | B6: Country has NBSAP commitments loaded | C6: =IF(SUM(Taxonomy!G5:G19)>0,"Pass","Fail – load Market_Examples for this country")
A7: 3 | B7: All 15 sub-themes scored (C1, C2, C4 entered) | C7: =IF(COUNT(Scoring!J5:J19)=15,"Pass",15-COUNT(Scoring!J5:J19)&" missing")
A8: 4 | B8: Weights total 100% | C8: =IF(ABS(Rubric!C10-1)<0.0001,"Pass","Fail")
A9: 5 | B9: C2 cap respected (C2 ≤ 2 where C1 ≤ 2) | C9: =IF(SUMPRODUCT((Scoring!E5:E19<>"")*(Scoring!E5:E19<=2)*(Scoring!F5:F19>2))=0,"Pass","Fail")
A10: 6 | B10: Every evidence item mapped | C10: =IF(COUNTA(Evidence_Log!A5:A304)=COUNTA(NBSAP_Mapping!A5:A304),"Pass","Mismatch")
A11: 7 | B11: Every evidence item has source, page and quote | C11: =IF(SUMPRODUCT((Evidence_Log!A5:A304<>"")*((Evidence_Log!B5:B304="")+(Evidence_Log!C5:C304="")+(Evidence_Log!D5:D304="")))=0,"Pass","Fail")
A12: 8 | B12: Mapping IDs exist in taxonomy | C12: =IF(SUMPRODUCT((NBSAP_Mapping!D5:D304<>"")*(NBSAP_Mapping!D5:D304<>"XC")*ISNA(MATCH(NBSAP_Mapping!D5:D304,Taxonomy!C5:C19,0)))=0,"Pass","Fail")
A13: 9 | B13: EXAMPLE rows deleted | C13: =IF(COUNTIF(Evidence_Log!G:G,"EXAMPLE*")+COUNTIF(NBSAP_Mapping!H:H,"EXAMPLE*")+COUNTIF(Sources!I:I,"EXAMPLE*")+COUNTIF(Client_Exposure!I:I,"*EXAMPLE")=0,"Pass","Delete EXAMPLE rows")
